{
  "items": [
    {
      "branch_product_id": null,
      "brand": null,
      "catalog_product_id": "338079",
      "category_paths": [
        "Vegetable > Salads & Dressings"
      ],
      "currency": "USD",
      "departments": [
        "Vegetable"
      ],
      "description": null,
      "first_seen": "2026-07-23",
      "has_price_change": false,
      "image_url": "https://galasupermarkets.com/api/content/images/thumbs/0254166_earthbound-farm-hh-bby-spin-and-arugula_300.jpeg",
      "is_active": true,
      "is_current": true,
      "is_visible": true,
      "is_weighable": false,
      "last_seen": "2026-07-23",
      "latest_promotion_count": 0,
      "latest_regular_price": 5.69,
      "name": "Earthbound Farm Organic Baby Spinach & Baby Arugula, 5 Oz",
      "observations": [
        {
          "catalog": {
            "current_price": 5.69,
            "display_price": "$5.69 / each",
            "is_out_of_stock": null,
            "original_display_price": null,
            "promotion_ids": [],
            "regular_price": 5.69
          },
          "date": "2026-07-23",
          "promotions": []
        }
      ],
      "observed_days": 1,
      "product_key": "gala:store:6:product:270899",
      "retailer_product_id": "270899",
      "sku": "0003260190186",
      "source_id": "270899",
      "source_url": "https://galasupermarkets.com/Freeport-Merrick/category/10373",
      "sp_id": "338079",
      "unit_of_measure": "each",
      "unit_resolution": null,
      "weight": null
    },
    {
      "branch_product_id": null,
      "brand": null,
      "catalog_product_id": "339144",
      "category_paths": [
        "Grocery > Baking Needs > Crumbs & Crusts"
      ],
      "currency": "USD",
      "departments": [
        "Grocery"
      ],
      "description": "Bread Crumbs Garlic & Herb",
      "first_seen": "2026-07-23",
      "has_price_change": false,
      "image_url": "https://galasupermarkets.com/api/content/images/thumbs/0253662_progresso-garlicherb-brd-cr_300.jpeg",
      "is_active": true,
      "is_current": true,
      "is_visible": true,
      "is_weighable": false,
      "last_seen": "2026-07-23",
      "latest_promotion_count": 0,
      "latest_regular_price": 3.29,
      "name": "Progresso Bread Crumbs Garlic & Herb, 15 Oz",
      "observations": [
        {
          "catalog": {
            "current_price": 3.29,
            "display_price": "$3.29",
            "is_out_of_stock": null,
            "original_display_price": null,
            "promotion_ids": [],
            "regular_price": 3.29
          },
          "date": "2026-07-23",
          "promotions": []
        }
      ],
      "observed_days": 1,
      "product_key": "gala:store:6:product:271964",
      "retailer_product_id": "271964",
      "sku": "0004119689123",
      "source_id": "271964",
      "source_url": "https://galasupermarkets.com/Freeport-Merrick/category/10492",
      "sp_id": "339144",
      "unit_of_measure": null,
      "unit_resolution": null,
      "weight": null
    },
    {
      "branch_product_id": null,
      "brand": null,
      "catalog_product_id": "340189",
      "category_paths": [
        "Deli > Cold Cuts"
      ],
      "currency": "USD",
      "departments": [
        "Deli"
      ],
      "description": null,
      "first_seen": "2026-07-23",
      "has_price_change": false,
      "image_url": "https://galasupermarkets.com/api/content/images/thumbs/0241283_oscar-mayer-om-thick-bacon_300.jpeg",
      "is_active": true,
      "is_current": true,
      "is_visible": true,
      "is_weighable": false,
      "last_seen": "2026-07-23",
      "latest_promotion_count": 1,
      "latest_regular_price": 11.99,
      "name": "Oscar Mayer Thick Cut Bacon, 16 Oz",
      "observations": [
        {
          "catalog": {
            "current_price": 9.99,
            "display_price": "$9.99 / each",
            "is_out_of_stock": null,
            "original_display_price": "$11.99",
            "promotion_ids": [
              "sale:c04b8295c158da84"
            ],
            "regular_price": 11.99
          },
          "date": "2026-07-23",
          "promotions": [
            {
              "derivation_basis": "explicit P_v sale price",
              "derived_effective_unit_price": 9.99,
              "description": "Sale $9.99 (regular $11.99)",
              "promotion_id": "sale:c04b8295c158da84"
            }
          ]
        }
      ],
      "observed_days": 1,
      "product_key": "gala:store:6:product:273009",
      "retailer_product_id": "273009",
      "sku": "0004470001990",
      "source_id": "273009",
      "source_url": "https://galasupermarkets.com/Freeport-Merrick/category/11116",
      "sp_id": "340189",
      "unit_of_measure": "each",
      "unit_resolution": null,
      "weight": null
    },
    {
      "branch_product_id": null,
      "brand": null,
      "catalog_product_id": "342528",
      "category_paths": [
        "Deli > Deli Meat"
      ],
      "currency": "USD",
      "departments": [
        "Deli"
      ],
      "description": null,
      "first_seen": "2026-07-23",
      "has_price_change": false,
      "image_url": "https://galasupermarkets.com/api/content/images/thumbs/0251364_sabrett-all-beef-hot-sausage_300.jpeg",
      "is_active": true,
      "is_current": true,
      "is_visible": true,
      "is_weighable": false,
      "last_seen": "2026-07-23",
      "latest_promotion_count": 0,
      "latest_regular_price": 7.69,
      "name": "Sabrett Hot Sausage, 16 Oz",
      "observations": [
        {
          "catalog": {
            "current_price": 7.69,
            "display_price": "$7.69",
            "is_out_of_stock": null,
            "original_display_price": null,
            "promotion_ids": [],
            "regular_price": 7.69
          },
          "date": "2026-07-23",
          "promotions": []
        }
      ],
      "observed_days": 1,
      "product_key": "gala:store:6:product:275348",
      "retailer_product_id": "275348",
      "sku": "0007433800479",
      "source_id": "275348",
      "source_url": "https://galasupermarkets.com/Freeport-Merrick/category/10649",
      "sp_id": "342528",
      "unit_of_measure": null,
      "unit_resolution": null,
      "weight": null
    },
    {
      "branch_product_id": null,
      "brand": null,
      "catalog_product_id": "346085",
      "category_paths": [
        "Dairy > Yogurt"
      ],
      "currency": "USD",
      "departments": [
        "Dairy"
      ],
      "description": "Greek ogurt Pineapple",
      "first_seen": "2026-07-23",
      "has_price_change": false,
      "image_url": "https://galasupermarkets.com/api/content/images/thumbs/0239874_chobani-grk-2-lf-pineapple_300.jpeg",
      "is_active": true,
      "is_current": true,
      "is_visible": true,
      "is_weighable": false,
      "last_seen": "2026-07-23",
      "latest_promotion_count": 1,
      "latest_regular_price": 1.79,
      "name": "Chobani Greek Yogurt Pineapple 2%, 5.3 Oz",
      "observations": [
        {
          "catalog": {
            "current_price": 5.0,
            "display_price": "$5.00",
            "is_out_of_stock": null,
            "original_display_price": "$1.79",
            "promotion_ids": [
              "multi_buy:917811197afa9b45"
            ],
            "regular_price": 1.79
          },
          "date": "2026-07-23",
          "promotions": [
            {
              "derivation_basis": "explicit source quantity 3 for total $5",
              "derived_effective_unit_price": 1.6667,
              "description": "3 for $5",
              "promotion_id": "multi_buy:917811197afa9b45"
            }
          ]
        }
      ],
      "observed_days": 1,
      "product_key": "gala:store:6:product:278905",
      "retailer_product_id": "278905",
      "sku": "0089470001010",
      "source_id": "278905",
      "source_url": "https://galasupermarkets.com/Freeport-Merrick/category/10441",
      "sp_id": "346085",
      "unit_of_measure": null,
      "unit_resolution": null,
      "weight": null
    },
    {
      "branch_product_id": null,
      "brand": null,
      "catalog_product_id": "346608",
      "category_paths": [
        "Grocery > Canned Goods > Canned Vegetables"
      ],
      "currency": "USD",
      "departments": [
        "Grocery"
      ],
      "description": null,
      "first_seen": "2026-07-23",
      "has_price_change": false,
      "image_url": "https://galasupermarkets.com/api/content/images/thumbs/0232618_hot-pepper-la-morena-rajas_300.jpeg",
      "is_active": true,
      "is_current": true,
      "is_visible": true,
      "is_weighable": false,
      "last_seen": "2026-07-23",
      "latest_promotion_count": 0,
      "latest_regular_price": 1.59,
      "name": "La Morena sliced green pickled Jalapeno 7oz.",
      "observations": [
        {
          "catalog": {
            "current_price": 1.59,
            "display_price": "$1.59",
            "is_out_of_stock": null,
            "original_display_price": null,
            "promotion_ids": [],
            "regular_price": 1.59
          },
          "date": "2026-07-23",
          "promotions": []
        }
      ],
      "observed_days": 1,
      "product_key": "gala:store:6:product:279428",
      "retailer_product_id": "279428",
      "sku": "0072745200033",
      "source_id": "279428",
      "source_url": "https://galasupermarkets.com/Freeport-Merrick/category/10676",
      "sp_id": "346608",
      "unit_of_measure": null,
      "unit_resolution": null,
      "weight": null
    },
    {
      "branch_product_id": null,
      "brand": null,
      "catalog_product_id": "348137",
      "category_paths": [
        "Grocery > Baking Needs > Jel & Pudding"
      ],
      "currency": "USD",
      "departments": [
        "Grocery"
      ],
      "description": null,
      "first_seen": "2026-07-23",
      "has_price_change": false,
      "image_url": "https://galasupermarkets.com/api/content/images/thumbs/0245905_jell-o-jello-cherry_300.jpeg",
      "is_active": true,
      "is_current": true,
      "is_visible": true,
      "is_weighable": false,
      "last_seen": "2026-07-23",
      "latest_promotion_count": 0,
      "latest_regular_price": 2.29,
      "name": "Jell-O Gelatin Dessert Cherry, 3 Oz",
      "observations": [
        {
          "catalog": {
            "current_price": 2.29,
            "display_price": "$2.29",
            "is_out_of_stock": null,
            "original_display_price": null,
            "promotion_ids": [],
            "regular_price": 2.29
          },
          "date": "2026-07-23",
          "promotions": []
        }
      ],
      "observed_days": 1,
      "product_key": "gala:store:6:product:280957",
      "retailer_product_id": "280957",
      "sku": "0004300020003",
      "source_id": "280957",
      "source_url": "https://galasupermarkets.com/Freeport-Merrick/category/10499",
      "sp_id": "348137",
      "unit_of_measure": null,
      "unit_resolution": null,
      "weight": null
    },
    {
      "branch_product_id": null,
      "brand": null,
      "catalog_product_id": "350589",
      "category_paths": [
        "Grocery > Beans & Grains > Beans & Lentils"
      ],
      "currency": "USD",
      "departments": [
        "Grocery"
      ],
      "description": "Iberia Peas Yellow Split",
      "first_seen": "2026-07-23",
      "has_price_change": false,
      "image_url": "https://galasupermarkets.com/api/content/images/thumbs/0236606_iberia-peas-yellow-split_300.jpeg",
      "is_active": true,
      "is_current": true,
      "is_visible": true,
      "is_weighable": false,
      "last_seen": "2026-07-23",
      "latest_promotion_count": 0,
      "latest_regular_price": 1.69,
      "name": "Iberia Peas Yellow Split",
      "observations": [
        {
          "catalog": {
            "current_price": 1.69,
            "display_price": "$1.69",
            "is_out_of_stock": null,
            "original_display_price": null,
            "promotion_ids": [],
            "regular_price": 1.69
          },
          "date": "2026-07-23",
          "promotions": []
        }
      ],
      "observed_days": 1,
      "product_key": "gala:store:6:product:283409",
      "retailer_product_id": "283409",
      "sku": "0007566910671",
      "source_id": "283409",
      "source_url": "https://galasupermarkets.com/Freeport-Merrick/category/10482",
      "sp_id": "350589",
      "unit_of_measure": null,
      "unit_resolution": null,
      "weight": null
    },
    {
      "branch_product_id": null,
      "brand": null,
      "catalog_product_id": "351727",
      "category_paths": [
        "Grocery > Canned Goods > Canned Tomato"
      ],
      "currency": "USD",
      "departments": [
        "Grocery"
      ],
      "description": "Goya Tomato Paste",
      "first_seen": "2026-07-23",
      "has_price_change": false,
      "image_url": "https://galasupermarkets.com/api/content/images/thumbs/0235030_goya-tomato-paste_300.jpeg",
      "is_active": true,
      "is_current": true,
      "is_visible": true,
      "is_weighable": false,
      "last_seen": "2026-07-23",
      "latest_promotion_count": 0,
      "latest_regular_price": 4.29,
      "name": "Goya Tomato Paste",
      "observations": [
        {
          "catalog": {
            "current_price": 4.29,
            "display_price": "$4.29",
            "is_out_of_stock": null,
            "original_display_price": null,
            "promotion_ids": [],
            "regular_price": 4.29
          },
          "date": "2026-07-23",
          "promotions": []
        }
      ],
      "observed_days": 1,
      "product_key": "gala:store:6:product:284547",
      "retailer_product_id": "284547",
      "sku": "0004133103968",
      "source_id": "284547",
      "source_url": "https://galasupermarkets.com/Freeport-Merrick/category/11117",
      "sp_id": "351727",
      "unit_of_measure": null,
      "unit_resolution": null,
      "weight": null
    },
    {
      "branch_product_id": null,
      "brand": null,
      "catalog_product_id": "351843",
      "category_paths": [
        "Grocery > Snacks > Variety Snacks"
      ],
      "currency": "USD",
      "departments": [
        "Grocery"
      ],
      "description": "Utz Party Mix Barrel",
      "first_seen": "2026-07-23",
      "has_price_change": false,
      "image_url": "https://galasupermarkets.com/api/content/images/thumbs/0243068_utz-party-mix-barrel_300.jpeg",
      "is_active": true,
      "is_current": true,
      "is_visible": true,
      "is_weighable": false,
      "last_seen": "2026-07-23",
      "latest_promotion_count": 1,
      "latest_regular_price": 9.99,
      "name": "Utz Party Mix, 26 Oz",
      "observations": [
        {
          "catalog": {
            "current_price": 6.99,
            "display_price": "$6.99",
            "is_out_of_stock": null,
            "original_display_price": "$9.99",
            "promotion_ids": [
              "sale:4a3389eb7e9bdb76"
            ],
            "regular_price": 9.99
          },
          "date": "2026-07-23",
          "promotions": [
            {
              "derivation_basis": "explicit P_v sale price",
              "derived_effective_unit_price": 6.99,
              "description": "Sale $6.99 (regular $9.99)",
              "promotion_id": "sale:4a3389eb7e9bdb76"
            }
          ]
        }
      ],
      "observed_days": 1,
      "product_key": "gala:store:6:product:284663",
      "retailer_product_id": "284663",
      "sku": "0004178001328",
      "source_id": "284663",
      "source_url": "https://galasupermarkets.com/Freeport-Merrick/category/10582",
      "sp_id": "351843",
      "unit_of_measure": null,
      "unit_resolution": null,
      "weight": null
    },
    {
      "branch_product_id": null,
      "brand": null,
      "catalog_product_id": "351877",
      "category_paths": [
        "Frozen > Pancakes & Waffles"
      ],
      "currency": "USD",
      "departments": [
        "Frozen"
      ],
      "description": "Kellog's Eggo Pancake Minis",
      "first_seen": "2026-07-23",
      "has_price_change": false,
      "image_url": "https://galasupermarkets.com/api/content/images/thumbs/0249286_kelloggs-eggo-buttermilk-mini-pancake_300.jpeg",
      "is_active": true,
      "is_current": true,
      "is_visible": true,
      "is_weighable": false,
      "last_seen": "2026-07-23",
      "latest_promotion_count": 0,
      "latest_regular_price": 3.99,
      "name": "Kellog's Eggo Pancake Minis, 14.1 oz",
      "observations": [
        {
          "catalog": {
            "current_price": 3.99,
            "display_price": "$3.99 / each",
            "is_out_of_stock": null,
            "original_display_price": null,
            "promotion_ids": [],
            "regular_price": 3.99
          },
          "date": "2026-07-23",
          "promotions": []
        }
      ],
      "observed_days": 1,
      "product_key": "gala:store:6:product:284697",
      "retailer_product_id": "284697",
      "sku": "0003800026066",
      "source_id": "284697",
      "source_url": "https://galasupermarkets.com/Freeport-Merrick/category/11075",
      "sp_id": "351877",
      "unit_of_measure": "each",
      "unit_resolution": null,
      "weight": null
    },
    {
      "branch_product_id": null,
      "brand": null,
      "catalog_product_id": "352244",
      "category_paths": [
        "Frozen > Ice Cream & Sorbet > Ice Cream Tubs"
      ],
      "currency": "USD",
      "departments": [
        "Frozen"
      ],
      "description": "Friendly Cherry Vanill",
      "first_seen": "2026-07-23",
      "has_price_change": false,
      "image_url": "https://galasupermarkets.com/api/content/images/thumbs/0239831_friendlys-friendly-cherry-vanill_300.jpeg",
      "is_active": true,
      "is_current": true,
      "is_visible": true,
      "is_weighable": false,
      "last_seen": "2026-07-23",
      "latest_promotion_count": 1,
      "latest_regular_price": 7.29,
      "name": "Friendly's Cherry Vanilla Premium Ice Cream, 1.5 Qt",
      "observations": [
        {
          "catalog": {
            "current_price": 4.99,
            "display_price": "$4.99",
            "is_out_of_stock": null,
            "original_display_price": "$7.29",
            "promotion_ids": [
              "sale:bfb8c0fcf569ab8f"
            ],
            "regular_price": 7.29
          },
          "date": "2026-07-23",
          "promotions": [
            {
              "derivation_basis": "explicit P_v sale price",
              "derived_effective_unit_price": 4.99,
              "description": "Sale $4.99 (regular $7.29)",
              "promotion_id": "sale:bfb8c0fcf569ab8f"
            }
          ]
        }
      ],
      "observed_days": 1,
      "product_key": "gala:store:6:product:285064",
      "retailer_product_id": "285064",
      "sku": "0002983900463",
      "source_id": "285064",
      "source_url": "https://galasupermarkets.com/Freeport-Merrick/category/10457",
      "sp_id": "352244",
      "unit_of_measure": null,
      "unit_resolution": null,
      "weight": null
    },
    {
      "branch_product_id": null,
      "brand": null,
      "catalog_product_id": "353500",
      "category_paths": [
        "Grocery > Snacks > Tortilla Chips"
      ],
      "currency": "USD",
      "departments": [
        "Grocery"
      ],
      "description": "Crma Centro Americ",
      "first_seen": "2026-07-23",
      "has_price_change": false,
      "image_url": "https://galasupermarkets.com/api/content/images/thumbs/0253528_crema-la-centro-americana-crma-centro-americ_300.jpeg",
      "is_active": true,
      "is_current": true,
      "is_visible": true,
      "is_weighable": false,
      "last_seen": "2026-07-23",
      "latest_promotion_count": 0,
      "latest_regular_price": 4.99,
      "name": "Crema La Centro Americana",
      "observations": [
        {
          "catalog": {
            "current_price": 4.99,
            "display_price": "$4.99",
            "is_out_of_stock": null,
            "original_display_price": null,
            "promotion_ids": [],
            "regular_price": 4.99
          },
          "date": "2026-07-23",
          "promotions": []
        }
      ],
      "observed_days": 1,
      "product_key": "gala:store:6:product:286320",
      "retailer_product_id": "286320",
      "sku": "0087659300046",
      "source_id": "286320",
      "source_url": "https://galasupermarkets.com/Freeport-Merrick/category/10628",
      "sp_id": "353500",
      "unit_of_measure": null,
      "unit_resolution": null,
      "weight": null
    },
    {
      "branch_product_id": null,
      "brand": null,
      "catalog_product_id": "353986",
      "category_paths": [
        "Deli > Deli Meat"
      ],
      "currency": "USD",
      "departments": [
        "Deli"
      ],
      "description": null,
      "first_seen": "2026-07-23",
      "has_price_change": false,
      "image_url": "https://galasupermarkets.com/api/content/images/thumbs/0249409_cooked-salami-jamonada_300.jpeg",
      "is_active": true,
      "is_current": true,
      "is_visible": true,
      "is_weighable": false,
      "last_seen": "2026-07-23",
      "latest_promotion_count": 0,
      "latest_regular_price": 10.29,
      "name": "Don Pedro Jamonada Cooked Salami",
      "observations": [
        {
          "catalog": {
            "current_price": 10.29,
            "display_price": "$10.29",
            "is_out_of_stock": null,
            "original_display_price": null,
            "promotion_ids": [],
            "regular_price": 10.29
          },
          "date": "2026-07-23",
          "promotions": []
        }
      ],
      "observed_days": 1,
      "product_key": "gala:store:6:product:286806",
      "retailer_product_id": "286806",
      "sku": "0078611900106",
      "source_id": "286806",
      "source_url": "https://galasupermarkets.com/Freeport-Merrick/category/10649",
      "sp_id": "353986",
      "unit_of_measure": null,
      "unit_resolution": null,
      "weight": null
    },
    {
      "branch_product_id": null,
      "brand": null,
      "catalog_product_id": "356240",
      "category_paths": [
        "Grocery > Beverages > Juices"
      ],
      "currency": "USD",
      "departments": [
        "Grocery"
      ],
      "description": "Motts Clam Juice Preparado",
      "first_seen": "2026-07-23",
      "has_price_change": false,
      "image_url": "https://galasupermarkets.com/api/content/images/thumbs/0275358_clamato-juice-preparado_300.jpeg",
      "is_active": true,
      "is_current": true,
      "is_visible": true,
      "is_weighable": false,
      "last_seen": "2026-07-23",
      "latest_promotion_count": 0,
      "latest_regular_price": 4.49,
      "name": "Clamato Juice Preparado",
      "observations": [
        {
          "catalog": {
            "current_price": 4.49,
            "display_price": "$4.49",
            "is_out_of_stock": null,
            "original_display_price": null,
            "promotion_ids": [],
            "regular_price": 4.49
          },
          "date": "2026-07-23",
          "promotions": []
        }
      ],
      "observed_days": 1,
      "product_key": "gala:store:6:product:289060",
      "retailer_product_id": "289060",
      "sku": "0001480000360",
      "source_id": "289060",
      "source_url": "https://galasupermarkets.com/Freeport-Merrick/category/10618",
      "sp_id": "356240",
      "unit_of_measure": null,
      "unit_resolution": null,
      "weight": null
    },
    {
      "branch_product_id": null,
      "brand": null,
      "catalog_product_id": "356845",
      "category_paths": [
        "Grocery > Spices"
      ],
      "currency": "USD",
      "departments": [
        "Grocery"
      ],
      "description": null,
      "first_seen": "2026-07-23",
      "has_price_change": false,
      "image_url": "https://galasupermarkets.com/api/content/images/thumbs/0249762_malher-restomate_300.jpeg",
      "is_active": true,
      "is_current": true,
      "is_visible": true,
      "is_weighable": false,
      "last_seen": "2026-07-23",
      "latest_promotion_count": 0,
      "latest_regular_price": 3.89,
      "name": "Malher Tomato And Beef Flavor Bouillon, 7 Oz",
      "observations": [
        {
          "catalog": {
            "current_price": 3.89,
            "display_price": "$3.89",
            "is_out_of_stock": null,
            "original_display_price": null,
            "promotion_ids": [],
            "regular_price": 3.89
          },
          "date": "2026-07-23",
          "promotions": []
        }
      ],
      "observed_days": 1,
      "product_key": "gala:store:6:product:289665",
      "retailer_product_id": "289665",
      "sku": "0008967400067",
      "source_id": "289665",
      "source_url": "https://galasupermarkets.com/Freeport-Merrick/category/10517",
      "sp_id": "356845",
      "unit_of_measure": null,
      "unit_resolution": null,
      "weight": null
    },
    {
      "branch_product_id": null,
      "brand": null,
      "catalog_product_id": "358678",
      "category_paths": [
        "Grocery > Baking Needs > Oil & Shortening"
      ],
      "currency": "USD",
      "departments": [
        "Grocery"
      ],
      "description": "Extra Virgin Olive Oil",
      "first_seen": "2026-07-23",
      "has_price_change": false,
      "image_url": "https://galasupermarkets.com/api/content/images/thumbs/0241976_filippo-berio-fil-berio-ex-vir-olv-oil-3lt_300.jpeg",
      "is_active": true,
      "is_current": true,
      "is_visible": true,
      "is_weighable": false,
      "last_seen": "2026-07-23",
      "latest_promotion_count": 0,
      "latest_regular_price": 37.99,
      "name": "Filippo Berio Extra Virgin Olive Oil, 101.4 fl oz",
      "observations": [
        {
          "catalog": {
            "current_price": 37.99,
            "display_price": "$37.99",
            "is_out_of_stock": null,
            "original_display_price": null,
            "promotion_ids": [],
            "regular_price": 37.99
          },
          "date": "2026-07-23",
          "promotions": []
        }
      ],
      "observed_days": 1,
      "product_key": "gala:store:6:product:291498",
      "retailer_product_id": "291498",
      "sku": "0004173601011",
      "source_id": "291498",
      "source_url": "https://galasupermarkets.com/Freeport-Merrick/category/10506",
      "sp_id": "358678",
      "unit_of_measure": null,
      "unit_resolution": null,
      "weight": null
    },
    {
      "branch_product_id": null,
      "brand": null,
      "catalog_product_id": "359052",
      "category_paths": [
        "Health & Beauty > Shampoo & Conditioner"
      ],
      "currency": "USD",
      "departments": [
        "Health & Beauty"
      ],
      "description": "Grisi Manzanilla Conditioner",
      "first_seen": "2026-07-23",
      "has_price_change": false,
      "image_url": "https://galasupermarkets.com/api/content/images/thumbs/0245152_grisi-manzanilla-conditioner_300.jpeg",
      "is_active": true,
      "is_current": true,
      "is_visible": true,
      "is_weighable": false,
      "last_seen": "2026-07-23",
      "latest_promotion_count": 0,
      "latest_regular_price": 4.69,
      "name": "Grisi Manzanilla Conditioner, 13.5 Fl Oz",
      "observations": [
        {
          "catalog": {
            "current_price": 4.69,
            "display_price": "$4.69",
            "is_out_of_stock": null,
            "original_display_price": null,
            "promotion_ids": [],
            "regular_price": 4.69
          },
          "date": "2026-07-23",
          "promotions": []
        }
      ],
      "observed_days": 1,
      "product_key": "gala:store:6:product:291872",
      "retailer_product_id": "291872",
      "sku": "0003783608004",
      "source_id": "291872",
      "source_url": "https://galasupermarkets.com/Freeport-Merrick/category/10536",
      "sp_id": "359052",
      "unit_of_measure": null,
      "unit_resolution": null,
      "weight": null
    },
    {
      "branch_product_id": null,
      "brand": null,
      "catalog_product_id": "360029",
      "category_paths": [
        "Vegetable > Broccoli & Cauliflower"
      ],
      "currency": "USD",
      "departments": [
        "Vegetable"
      ],
      "description": "Broccoli Rabe",
      "first_seen": "2026-07-23",
      "has_price_change": false,
      "image_url": "https://galasupermarkets.com/api/content/images/thumbs/0182668_broccoli-rabe_300.jpeg",
      "is_active": true,
      "is_current": true,
      "is_visible": true,
      "is_weighable": true,
      "last_seen": "2026-07-23",
      "latest_promotion_count": 0,
      "latest_regular_price": 4.99,
      "name": "Broccoli Rabe",
      "observations": [
        {
          "catalog": {
            "current_price": 4.99,
            "display_price": "$4.99 / lb",
            "is_out_of_stock": null,
            "original_display_price": null,
            "promotion_ids": [],
            "regular_price": 4.99
          },
          "date": "2026-07-23",
          "promotions": []
        }
      ],
      "observed_days": 1,
      "product_key": "gala:store:6:product:292849",
      "retailer_product_id": "292849",
      "sku": "0000000000864",
      "source_id": "292849",
      "source_url": "https://galasupermarkets.com/Freeport-Merrick/category/11049",
      "sp_id": "360029",
      "unit_of_measure": "lb",
      "unit_resolution": null,
      "weight": null
    },
    {
      "branch_product_id": null,
      "brand": null,
      "catalog_product_id": "362796",
      "category_paths": [
        "Grocery > Canned Goods > Canned Beans & Peas"
      ],
      "currency": "USD",
      "departments": [
        "Grocery"
      ],
      "description": "Goya Bean Black 47Oz",
      "first_seen": "2026-07-23",
      "has_price_change": false,
      "image_url": "https://galasupermarkets.com/api/content/images/thumbs/0254523_goya-bean-black-47oz_300.jpeg",
      "is_active": true,
      "is_current": true,
      "is_visible": true,
      "is_weighable": false,
      "last_seen": "2026-07-23",
      "latest_promotion_count": 0,
      "latest_regular_price": 4.49,
      "name": "Goya Black Beans Premium, 47 Oz",
      "observations": [
        {
          "catalog": {
            "current_price": 4.49,
            "display_price": "$4.49",
            "is_out_of_stock": null,
            "original_display_price": null,
            "promotion_ids": [],
            "regular_price": 4.49
          },
          "date": "2026-07-23",
          "promotions": []
        }
      ],
      "observed_days": 1,
      "product_key": "gala:store:6:product:295616",
      "retailer_product_id": "295616",
      "sku": "0004133102353",
      "source_id": "295616",
      "source_url": "https://galasupermarkets.com/Freeport-Merrick/category/11206",
      "sp_id": "362796",
      "unit_of_measure": null,
      "unit_resolution": null,
      "weight": null
    },
    {
      "branch_product_id": null,
      "brand": null,
      "catalog_product_id": "363876",
      "category_paths": [
        "Household > Pesticide"
      ],
      "currency": "USD",
      "departments": [
        "Household"
      ],
      "description": "Black Jack Household Indoor Fogger",
      "first_seen": "2026-07-23",
      "has_price_change": false,
      "image_url": "https://galasupermarkets.com/api/content/images/thumbs/0250800_black-jack-blk-jack-indoor-fogger-hero_300.jpeg",
      "is_active": true,
      "is_current": true,
      "is_visible": true,
      "is_weighable": false,
      "last_seen": "2026-07-23",
      "latest_promotion_count": 0,
      "latest_regular_price": 8.99,
      "name": "Black Jack Household Indoor Fogger, 7.5 oz",
      "observations": [
        {
          "catalog": {
            "current_price": 8.99,
            "display_price": "$8.99",
            "is_out_of_stock": null,
            "original_display_price": null,
            "promotion_ids": [],
            "regular_price": 8.99
          },
          "date": "2026-07-23",
          "promotions": []
        }
      ],
      "observed_days": 1,
      "product_key": "gala:store:6:product:296696",
      "retailer_product_id": "296696",
      "sku": "0007128100625",
      "source_id": "296696",
      "source_url": "https://galasupermarkets.com/Freeport-Merrick/category/10543",
      "sp_id": "363876",
      "unit_of_measure": null,
      "unit_resolution": null,
      "weight": null
    },
    {
      "branch_product_id": null,
      "brand": null,
      "catalog_product_id": "551295",
      "category_paths": [
        "Household > Pet Food"
      ],
      "currency": "USD",
      "departments": [
        "Household"
      ],
      "description": null,
      "first_seen": "2026-07-23",
      "has_price_change": false,
      "image_url": "https://galasupermarkets.com/api/content/images/thumbs/0277176_temptations-tasty-chicken-flavor-cat-treats-16-oz_300.jpeg",
      "is_active": true,
      "is_current": true,
      "is_visible": true,
      "is_weighable": false,
      "last_seen": "2026-07-23",
      "latest_promotion_count": 0,
      "latest_regular_price": 8.99,
      "name": "Temptations Tasty Chicken Flavor Cat Treats, 16 Oz",
      "observations": [
        {
          "catalog": {
            "current_price": 8.99,
            "display_price": "$8.99",
            "is_out_of_stock": null,
            "original_display_price": null,
            "promotion_ids": [],
            "regular_price": 8.99
          },
          "date": "2026-07-23",
          "promotions": []
        }
      ],
      "observed_days": 1,
      "product_key": "gala:store:6:product:306852",
      "retailer_product_id": "306852",
      "sku": "0002310010755",
      "source_id": "306852",
      "source_url": "https://galasupermarkets.com/Freeport-Merrick/category/11198",
      "sp_id": "551295",
      "unit_of_measure": null,
      "unit_resolution": null,
      "weight": null
    },
    {
      "branch_product_id": null,
      "brand": null,
      "catalog_product_id": "550441",
      "category_paths": [
        "Household > Miscellaneous"
      ],
      "currency": "USD",
      "departments": [
        "Household"
      ],
      "description": "Hefty Baggies Sandwich Bags With Twist Ties , 150 pcs",
      "first_seen": "2026-07-23",
      "has_price_change": false,
      "image_url": "https://galasupermarkets.com/api/content/images/thumbs/0275034_hefty-baggies-sandwich-bags-with-twist-ties-150-pcs_300.jpeg",
      "is_active": true,
      "is_current": true,
      "is_visible": true,
      "is_weighable": false,
      "last_seen": "2026-07-23",
      "latest_promotion_count": 0,
      "latest_regular_price": 3.99,
      "name": "Hefty Baggies Sandwich Bags With Twist Ties , 150 pcs",
      "observations": [
        {
          "catalog": {
            "current_price": 3.99,
            "display_price": "$3.99",
            "is_out_of_stock": null,
            "original_display_price": null,
            "promotion_ids": [],
            "regular_price": 3.99
          },
          "date": "2026-07-23",
          "promotions": []
        }
      ],
      "observed_days": 1,
      "product_key": "gala:store:6:product:307494",
      "retailer_product_id": "307494",
      "sku": "0001370048100",
      "source_id": "307494",
      "source_url": "https://galasupermarkets.com/Freeport-Merrick/category/10544",
      "sp_id": "550441",
      "unit_of_measure": null,
      "unit_resolution": null,
      "weight": null
    },
    {
      "branch_product_id": null,
      "brand": null,
      "catalog_product_id": "552250",
      "category_paths": [
        "Grocery > Cereal & Breakfast"
      ],
      "currency": "USD",
      "departments": [
        "Grocery"
      ],
      "description": "Quaker Gl Free Orgnl Oatmeal",
      "first_seen": "2026-07-23",
      "has_price_change": false,
      "image_url": "https://galasupermarkets.com/api/content/images/thumbs/0248099_quaker-gl-free-orgnl-oatmeal_300.jpeg",
      "is_active": true,
      "is_current": true,
      "is_visible": true,
      "is_weighable": false,
      "last_seen": "2026-07-23",
      "latest_promotion_count": 0,
      "latest_regular_price": 7.49,
      "name": "Quaker Gluten Free Instant Oatmeal Original, 12.3 Oz",
      "observations": [
        {
          "catalog": {
            "current_price": 7.49,
            "display_price": "$7.49",
            "is_out_of_stock": null,
            "original_display_price": null,
            "promotion_ids": [],
            "regular_price": 7.49
          },
          "date": "2026-07-23",
          "promotions": []
        }
      ],
      "observed_days": 1,
      "product_key": "gala:store:6:product:308693",
      "retailer_product_id": "308693",
      "sku": "0003000031798",
      "source_id": "308693",
      "source_url": "https://galasupermarkets.com/Freeport-Merrick/category/10486",
      "sp_id": "552250",
      "unit_of_measure": null,
      "unit_resolution": null,
      "weight": null
    },
    {
      "branch_product_id": null,
      "brand": null,
      "catalog_product_id": "554417",
      "category_paths": [
        "Household > Pet Food"
      ],
      "currency": "USD",
      "departments": [
        "Household"
      ],
      "description": "Fancy Feast Liver Chicken",
      "first_seen": "2026-07-23",
      "has_price_change": false,
      "image_url": "https://galasupermarkets.com/api/content/images/thumbs/0236987_fancy-feast-liver-chicken_300.jpeg",
      "is_active": true,
      "is_current": true,
      "is_visible": true,
      "is_weighable": false,
      "last_seen": "2026-07-23",
      "latest_promotion_count": 0,
      "latest_regular_price": 1.29,
      "name": "Fancy Feast Tender Liver & Chicken Feast Classic Gourmet Cat Food, 3 Oz",
      "observations": [
        {
          "catalog": {
            "current_price": 1.29,
            "display_price": "$1.29",
            "is_out_of_stock": null,
            "original_display_price": null,
            "promotion_ids": [],
            "regular_price": 1.29
          },
          "date": "2026-07-23",
          "promotions": []
        }
      ],
      "observed_days": 1,
      "product_key": "gala:store:6:product:311584",
      "retailer_product_id": "311584",
      "sku": "0005000042904",
      "source_id": "311584",
      "source_url": "https://galasupermarkets.com/Freeport-Merrick/category/11198",
      "sp_id": "554417",
      "unit_of_measure": null,
      "unit_resolution": null,
      "weight": null
    },
    {
      "branch_product_id": null,
      "brand": null,
      "catalog_product_id": "543342",
      "category_paths": [
        "Dairy > Cheese"
      ],
      "currency": "USD",
      "departments": [
        "Dairy"
      ],
      "description": null,
      "first_seen": "2026-07-23",
      "has_price_change": false,
      "image_url": "https://galasupermarkets.com/api/content/images/thumbs/0239396_athenos-fatfree-crumbl-feta_300.jpeg",
      "is_active": true,
      "is_current": true,
      "is_visible": true,
      "is_weighable": false,
      "last_seen": "2026-07-23",
      "latest_promotion_count": 0,
      "latest_regular_price": 5.99,
      "name": "Athenos Fat Free Feta Cheese, 5 Oz",
      "observations": [
        {
          "catalog": {
            "current_price": 5.99,
            "display_price": "$5.99",
            "is_out_of_stock": null,
            "original_display_price": null,
            "promotion_ids": [],
            "regular_price": 5.99
          },
          "date": "2026-07-23",
          "promotions": []
        }
      ],
      "observed_days": 1,
      "product_key": "gala:store:6:product:335570",
      "retailer_product_id": "335570",
      "sku": "0007027729115",
      "source_id": "335570",
      "source_url": "https://galasupermarkets.com/Freeport-Merrick/category/10440",
      "sp_id": "543342",
      "unit_of_measure": null,
      "unit_resolution": null,
      "weight": null
    },
    {
      "branch_product_id": null,
      "brand": null,
      "catalog_product_id": "592190",
      "category_paths": [
        "Vegetable > Root Vegetables"
      ],
      "currency": "USD",
      "departments": [
        "Vegetable"
      ],
      "description": null,
      "first_seen": "2026-07-23",
      "has_price_change": false,
      "image_url": "https://galasupermarkets.com/api/content/images/thumbs/0188088_fresh-ginger-per-lb_300.jpeg",
      "is_active": true,
      "is_current": true,
      "is_visible": true,
      "is_weighable": true,
      "last_seen": "2026-07-23",
      "latest_promotion_count": 0,
      "latest_regular_price": 2.69,
      "name": "Fresh Ginger Per Lb",
      "observations": [
        {
          "catalog": {
            "current_price": 2.69,
            "display_price": "$2.69 / lb",
            "is_out_of_stock": null,
            "original_display_price": null,
            "promotion_ids": [],
            "regular_price": 2.69
          },
          "date": "2026-07-23",
          "promotions": []
        }
      ],
      "observed_days": 1,
      "product_key": "gala:store:6:product:355796",
      "retailer_product_id": "355796",
      "sku": "0000000004612",
      "source_id": "355796",
      "source_url": "https://galasupermarkets.com/Freeport-Merrick/category/11072",
      "sp_id": "592190",
      "unit_of_measure": "lb",
      "unit_resolution": null,
      "weight": null
    },
    {
      "branch_product_id": null,
      "brand": null,
      "catalog_product_id": "346769",
      "category_paths": [
        "Meat > Beef & Pork"
      ],
      "currency": "USD",
      "departments": [
        "Meat"
      ],
      "description": null,
      "first_seen": "2026-07-23",
      "has_price_change": false,
      "image_url": "https://galasupermarkets.com/api/content/images/thumbs/0182516_kj-beef-loin-tbone-steak_300.jpeg",
      "is_active": true,
      "is_current": true,
      "is_visible": true,
      "is_weighable": true,
      "last_seen": "2026-07-23",
      "latest_promotion_count": 0,
      "latest_regular_price": 16.99,
      "name": "T-BONE STEAK BEEF LOIN",
      "observations": [
        {
          "catalog": {
            "current_price": 16.99,
            "display_price": "$16.99 / lb",
            "is_out_of_stock": null,
            "original_display_price": null,
            "promotion_ids": [],
            "regular_price": 16.99
          },
          "date": "2026-07-23",
          "promotions": []
        }
      ],
      "observed_days": 1,
      "product_key": "gala:store:6:product:372905",
      "retailer_product_id": "372905",
      "sku": "0020136900000",
      "source_id": "372905",
      "source_url": "https://galasupermarkets.com/Freeport-Merrick/category/10647",
      "sp_id": "346769",
      "unit_of_measure": "lb",
      "unit_resolution": null,
      "weight": null
    }
  ],
  "schema_version": "1.1"
}
