{
  "items": [
    {
      "branch_product_id": null,
      "brand": null,
      "catalog_product_id": "336162",
      "category_paths": [
        "Bakery > Bread & Bagels"
      ],
      "currency": "USD",
      "departments": [
        "Bakery"
      ],
      "description": null,
      "first_seen": "2026-07-23",
      "has_price_change": false,
      "image_url": "https://galasupermarkets.com/api/content/images/thumbs/0275177_pepperidge-farm-soft-white-hamburger-buns-145-oz_300.jpeg",
      "is_active": true,
      "is_current": true,
      "is_visible": true,
      "is_weighable": false,
      "last_seen": "2026-07-24",
      "latest_promotion_count": 1,
      "latest_regular_price": 4.29,
      "name": "Pepperidge Farm Soft White Hamburger Buns, 14.5 Oz",
      "observations": [
        {
          "catalog": {
            "current_price": 3.99,
            "display_price": "$3.99",
            "is_out_of_stock": null,
            "original_display_price": "$4.29",
            "promotion_ids": [
              "sale:3cc3c285e7963809"
            ],
            "regular_price": 4.29
          },
          "date": "2026-07-23",
          "promotions": [
            {
              "derivation_basis": "explicit P_v sale price",
              "derived_effective_unit_price": 3.99,
              "description": "Sale $3.99 (regular $4.29)",
              "promotion_id": "sale:3cc3c285e7963809"
            }
          ]
        },
        {
          "catalog": {
            "current_price": 7.0,
            "display_price": "$7.00",
            "is_out_of_stock": null,
            "original_display_price": "$4.29",
            "promotion_ids": [
              "multi_buy:33261c235fdaec3f"
            ],
            "regular_price": 4.29
          },
          "date": "2026-07-24",
          "promotions": [
            {
              "derivation_basis": "explicit source quantity 2 for total $7",
              "derived_effective_unit_price": 3.5,
              "description": "2 for $7",
              "promotion_id": "multi_buy:33261c235fdaec3f"
            }
          ]
        }
      ],
      "observed_days": 2,
      "product_key": "gala:store:6:product:268982",
      "retailer_product_id": "268982",
      "sku": "0001410007187",
      "source_id": "268982",
      "source_url": "https://galasupermarkets.com/Freeport-Merrick/category/10466",
      "sp_id": "336162",
      "unit_of_measure": null,
      "unit_resolution": null,
      "weight": null
    },
    {
      "branch_product_id": null,
      "brand": null,
      "catalog_product_id": "336166",
      "category_paths": [
        "Grocery > Snacks > Cookies"
      ],
      "currency": "USD",
      "departments": [
        "Grocery"
      ],
      "description": "Pep Farm Choc Chnk Chesapeak",
      "first_seen": "2026-07-23",
      "has_price_change": false,
      "image_url": "https://galasupermarkets.com/api/content/images/thumbs/0275194_pepperidge-farm-chesapeake-crispy-chesapeake-dark-chocolate-pecan-cookies-72-oz_300.jpeg",
      "is_active": true,
      "is_current": true,
      "is_visible": true,
      "is_weighable": false,
      "last_seen": "2026-07-24",
      "latest_promotion_count": 0,
      "latest_regular_price": 5.99,
      "name": "Pepperidge Farm Chesapeake Crispy Chesapeake Dark Chocolate Pecan Cookies, 7.2 Oz",
      "observations": [
        {
          "catalog": {
            "current_price": 5.99,
            "display_price": "$5.99",
            "is_out_of_stock": null,
            "original_display_price": null,
            "promotion_ids": [],
            "regular_price": 5.99
          },
          "date": "2026-07-23",
          "promotions": []
        },
        {
          "catalog": {
            "current_price": 5.99,
            "display_price": "$5.99",
            "is_out_of_stock": null,
            "original_display_price": null,
            "promotion_ids": [],
            "regular_price": 5.99
          },
          "date": "2026-07-24",
          "promotions": []
        }
      ],
      "observed_days": 2,
      "product_key": "gala:store:6:product:268986",
      "retailer_product_id": "268986",
      "sku": "0001410007708",
      "source_id": "268986",
      "source_url": "https://galasupermarkets.com/Freeport-Merrick/category/10469",
      "sp_id": "336166",
      "unit_of_measure": null,
      "unit_resolution": null,
      "weight": null
    },
    {
      "branch_product_id": null,
      "brand": null,
      "catalog_product_id": "336699",
      "category_paths": [
        "Frozen > Frozen Vegetables"
      ],
      "currency": "USD",
      "departments": [
        "Frozen"
      ],
      "description": "Green Giant Stmr Broc Cuts",
      "first_seen": "2026-07-23",
      "has_price_change": false,
      "image_url": "https://galasupermarkets.com/api/content/images/thumbs/0276537_green-giant-steamers-broccoli-cuts-12-oz_300.jpeg",
      "is_active": true,
      "is_current": true,
      "is_visible": true,
      "is_weighable": false,
      "last_seen": "2026-07-24",
      "latest_promotion_count": 0,
      "latest_regular_price": 2.79,
      "name": "Green Giant Steamers Broccoli Cuts 12 Oz",
      "observations": [
        {
          "catalog": {
            "current_price": 2.79,
            "display_price": "$2.79",
            "is_out_of_stock": null,
            "original_display_price": null,
            "promotion_ids": [],
            "regular_price": 2.79
          },
          "date": "2026-07-23",
          "promotions": []
        },
        {
          "catalog": {
            "current_price": 2.79,
            "display_price": "$2.79",
            "is_out_of_stock": null,
            "original_display_price": null,
            "promotion_ids": [],
            "regular_price": 2.79
          },
          "date": "2026-07-24",
          "promotions": []
        }
      ],
      "observed_days": 2,
      "product_key": "gala:store:6:product:269519",
      "retailer_product_id": "269519",
      "sku": "0002000027332",
      "source_id": "269519",
      "source_url": "https://galasupermarkets.com/Freeport-Merrick/category/10465",
      "sp_id": "336699",
      "unit_of_measure": null,
      "unit_resolution": null,
      "weight": null
    },
    {
      "branch_product_id": null,
      "brand": null,
      "catalog_product_id": "337759",
      "category_paths": [
        "Grocery > Snacks > Chips"
      ],
      "currency": "USD",
      "departments": [
        "Grocery"
      ],
      "description": "Stacys Simply Naked Pita",
      "first_seen": "2026-07-23",
      "has_price_change": false,
      "image_url": "https://galasupermarkets.com/api/content/images/thumbs/0238331_stacys-stacys-simply-naked-pita_300.jpeg",
      "is_active": true,
      "is_current": true,
      "is_visible": true,
      "is_weighable": false,
      "last_seen": "2026-07-24",
      "latest_promotion_count": 0,
      "latest_regular_price": 3.99,
      "name": "Stacy's Pita Chips, Simply Naked, 7.3 Oz",
      "observations": [
        {
          "catalog": {
            "current_price": 3.99,
            "display_price": "$3.99",
            "is_out_of_stock": null,
            "original_display_price": null,
            "promotion_ids": [],
            "regular_price": 3.99
          },
          "date": "2026-07-23",
          "promotions": []
        },
        {
          "catalog": {
            "current_price": 3.99,
            "display_price": "$3.99",
            "is_out_of_stock": null,
            "original_display_price": null,
            "promotion_ids": [],
            "regular_price": 3.99
          },
          "date": "2026-07-24",
          "promotions": []
        }
      ],
      "observed_days": 2,
      "product_key": "gala:store:6:product:270579",
      "retailer_product_id": "270579",
      "sku": "0002840056463",
      "source_id": "270579",
      "source_url": "https://galasupermarkets.com/Freeport-Merrick/category/10626",
      "sp_id": "337759",
      "unit_of_measure": null,
      "unit_resolution": null,
      "weight": null
    },
    {
      "branch_product_id": null,
      "brand": null,
      "catalog_product_id": "338042",
      "category_paths": [
        "Grocery > Canned Goods > Canned Tomato"
      ],
      "currency": "USD",
      "departments": [
        "Grocery"
      ],
      "description": null,
      "first_seen": "2026-07-23",
      "has_price_change": false,
      "image_url": "https://galasupermarkets.com/api/content/images/thumbs/0248034_bg-bg-sundried-tomatoes_300.jpeg",
      "is_active": true,
      "is_current": true,
      "is_visible": true,
      "is_weighable": false,
      "last_seen": "2026-07-24",
      "latest_promotion_count": 0,
      "latest_regular_price": 5.99,
      "name": "B&G Sundried Tomatoes, 7 Oz",
      "observations": [
        {
          "catalog": {
            "current_price": 5.99,
            "display_price": "$5.99",
            "is_out_of_stock": null,
            "original_display_price": null,
            "promotion_ids": [],
            "regular_price": 5.99
          },
          "date": "2026-07-23",
          "promotions": []
        },
        {
          "catalog": {
            "current_price": 5.99,
            "display_price": "$5.99",
            "is_out_of_stock": null,
            "original_display_price": null,
            "promotion_ids": [],
            "regular_price": 5.99
          },
          "date": "2026-07-24",
          "promotions": []
        }
      ],
      "observed_days": 2,
      "product_key": "gala:store:6:product:270862",
      "retailer_product_id": "270862",
      "sku": "0003150000625",
      "source_id": "270862",
      "source_url": "https://galasupermarkets.com/Freeport-Merrick/category/11117",
      "sp_id": "338042",
      "unit_of_measure": null,
      "unit_resolution": null,
      "weight": null
    },
    {
      "branch_product_id": null,
      "brand": null,
      "catalog_product_id": "340181",
      "category_paths": [
        "Household > Laundry > Bleach"
      ],
      "currency": "USD",
      "departments": [
        "Household"
      ],
      "description": "Clorox Colorld Nonchlor Blch",
      "first_seen": "2026-07-23",
      "has_price_change": false,
      "image_url": "https://galasupermarkets.com/api/content/images/thumbs/0240908_clorox-colorld-nonchlor-blch_300.jpeg",
      "is_active": true,
      "is_current": true,
      "is_visible": true,
      "is_weighable": false,
      "last_seen": "2026-07-24",
      "latest_promotion_count": 0,
      "latest_regular_price": 5.99,
      "name": "Clorox Colorld Nonchlor Blch",
      "observations": [
        {
          "catalog": {
            "current_price": 5.99,
            "display_price": "$5.99",
            "is_out_of_stock": null,
            "original_display_price": null,
            "promotion_ids": [],
            "regular_price": 5.99
          },
          "date": "2026-07-23",
          "promotions": []
        },
        {
          "catalog": {
            "current_price": 5.99,
            "display_price": "$5.99",
            "is_out_of_stock": null,
            "original_display_price": null,
            "promotion_ids": [],
            "regular_price": 5.99
          },
          "date": "2026-07-24",
          "promotions": []
        }
      ],
      "observed_days": 2,
      "product_key": "gala:store:6:product:273001",
      "retailer_product_id": "273001",
      "sku": "0004460031894",
      "source_id": "273001",
      "source_url": "https://galasupermarkets.com/Freeport-Merrick/category/10411",
      "sp_id": "340181",
      "unit_of_measure": null,
      "unit_resolution": null,
      "weight": null
    },
    {
      "branch_product_id": null,
      "brand": null,
      "catalog_product_id": "340392",
      "category_paths": [
        "Grocery > Dressing & Sauces > Mayonnaise"
      ],
      "currency": "USD",
      "departments": [
        "Grocery"
      ],
      "description": "Hellmanns Mayonnaise",
      "first_seen": "2026-07-23",
      "has_price_change": false,
      "image_url": "https://galasupermarkets.com/api/content/images/thumbs/0246020_hellmanns-hellmanns-mayonnaise_300.jpeg",
      "is_active": true,
      "is_current": true,
      "is_visible": true,
      "is_weighable": false,
      "last_seen": "2026-07-24",
      "latest_promotion_count": 0,
      "latest_regular_price": 5.99,
      "name": "Hellmann's Real Mayonnaise, 15 Oz",
      "observations": [
        {
          "catalog": {
            "current_price": 5.99,
            "display_price": "$5.99",
            "is_out_of_stock": null,
            "original_display_price": null,
            "promotion_ids": [],
            "regular_price": 5.99
          },
          "date": "2026-07-23",
          "promotions": []
        },
        {
          "catalog": {
            "current_price": 5.99,
            "display_price": "$5.99",
            "is_out_of_stock": null,
            "original_display_price": null,
            "promotion_ids": [],
            "regular_price": 5.99
          },
          "date": "2026-07-24",
          "promotions": []
        }
      ],
      "observed_days": 2,
      "product_key": "gala:store:6:product:273212",
      "retailer_product_id": "273212",
      "sku": "0004800121338",
      "source_id": "273212",
      "source_url": "https://galasupermarkets.com/Freeport-Merrick/category/10503",
      "sp_id": "340392",
      "unit_of_measure": null,
      "unit_resolution": null,
      "weight": null
    },
    {
      "branch_product_id": null,
      "brand": null,
      "catalog_product_id": "341530",
      "category_paths": [
        "Grocery > Beans & Grains > Beans & Lentils"
      ],
      "currency": "USD",
      "departments": [
        "Grocery"
      ],
      "description": "Jack Rabbit Lentils",
      "first_seen": "2026-07-24",
      "has_price_change": false,
      "image_url": "https://galasupermarkets.com/api/content/images/thumbs/682C5148-3962-44D2-88F9-3477E8CCEDD8_GF-image-coming-soon.jpeg",
      "is_active": true,
      "is_current": true,
      "is_visible": true,
      "is_weighable": false,
      "last_seen": "2026-07-24",
      "latest_promotion_count": 0,
      "latest_regular_price": 6.99,
      "name": "Jack Rabbit Lentils 64oz.",
      "observations": [
        {
          "catalog": null,
          "date": "2026-07-23",
          "promotions": []
        },
        {
          "catalog": {
            "current_price": 6.99,
            "display_price": "$6.99",
            "is_out_of_stock": null,
            "original_display_price": null,
            "promotion_ids": [],
            "regular_price": 6.99
          },
          "date": "2026-07-24",
          "promotions": []
        }
      ],
      "observed_days": 1,
      "product_key": "gala:store:6:product:274350",
      "retailer_product_id": "274350",
      "sku": "0007062000428",
      "source_id": "274350",
      "source_url": "https://galasupermarkets.com/Freeport-Merrick/category/10482",
      "sp_id": "341530",
      "unit_of_measure": null,
      "unit_resolution": null,
      "weight": null
    },
    {
      "branch_product_id": null,
      "brand": null,
      "catalog_product_id": "342743",
      "category_paths": [
        "Deli > Deli Meat"
      ],
      "currency": "USD",
      "departments": [
        "Deli"
      ],
      "description": null,
      "first_seen": "2026-07-23",
      "has_price_change": false,
      "image_url": "https://galasupermarkets.com/api/content/images/thumbs/0246847_hebrew-national-hebrew-nat-midget-salami_300.jpeg",
      "is_active": true,
      "is_current": true,
      "is_visible": true,
      "is_weighable": false,
      "last_seen": "2026-07-24",
      "latest_promotion_count": 1,
      "latest_regular_price": 9.99,
      "name": "Hebrew National Beef Salami, 12 Oz",
      "observations": [
        {
          "catalog": {
            "current_price": 7.99,
            "display_price": "$7.99",
            "is_out_of_stock": null,
            "original_display_price": "$9.99",
            "promotion_ids": [
              "sale:3ac3444870de3c59"
            ],
            "regular_price": 9.99
          },
          "date": "2026-07-23",
          "promotions": [
            {
              "derivation_basis": "explicit P_v sale price",
              "derived_effective_unit_price": 7.99,
              "description": "Sale $7.99 (regular $9.99)",
              "promotion_id": "sale:3ac3444870de3c59"
            }
          ]
        },
        {
          "catalog": {
            "current_price": 7.99,
            "display_price": "$7.99",
            "is_out_of_stock": null,
            "original_display_price": "$9.99",
            "promotion_ids": [
              "sale:3ac3444870de3c59"
            ],
            "regular_price": 9.99
          },
          "date": "2026-07-24",
          "promotions": [
            {
              "derivation_basis": "explicit P_v sale price",
              "derived_effective_unit_price": 7.99,
              "description": "Sale $7.99 (regular $9.99)",
              "promotion_id": "sale:3ac3444870de3c59"
            }
          ]
        }
      ],
      "observed_days": 2,
      "product_key": "gala:store:6:product:275563",
      "retailer_product_id": "275563",
      "sku": "0007495618240",
      "source_id": "275563",
      "source_url": "https://galasupermarkets.com/Freeport-Merrick/category/10649",
      "sp_id": "342743",
      "unit_of_measure": null,
      "unit_resolution": null,
      "weight": null
    },
    {
      "branch_product_id": null,
      "brand": null,
      "catalog_product_id": "342825",
      "category_paths": [
        "Grocery > Snacks > Popcorn"
      ],
      "currency": "USD",
      "departments": [
        "Grocery"
      ],
      "description": "Actii Popcorn Butter Lovers",
      "first_seen": "2026-07-23",
      "has_price_change": false,
      "image_url": "https://galasupermarkets.com/api/content/images/thumbs/0255350_act-ii-actii-popcorn-butter-lovers_300.jpeg",
      "is_active": true,
      "is_current": true,
      "is_visible": true,
      "is_weighable": false,
      "last_seen": "2026-07-24",
      "latest_promotion_count": 0,
      "latest_regular_price": 3.49,
      "name": "Act II Microwave Popcorn Butter Lovers, 8.25 Oz, 3 Ct",
      "observations": [
        {
          "catalog": {
            "current_price": 5.0,
            "display_price": "$5.00",
            "is_out_of_stock": null,
            "original_display_price": "$3.49",
            "promotion_ids": [
              "multi_buy:1036e2ccfd11c7c2"
            ],
            "regular_price": 3.49
          },
          "date": "2026-07-23",
          "promotions": [
            {
              "derivation_basis": "explicit source quantity 2 for total $5",
              "derived_effective_unit_price": 2.5,
              "description": "2 for $5",
              "promotion_id": "multi_buy:1036e2ccfd11c7c2"
            }
          ]
        },
        {
          "catalog": {
            "current_price": 3.49,
            "display_price": "$3.49 / each",
            "is_out_of_stock": null,
            "original_display_price": null,
            "promotion_ids": [],
            "regular_price": 3.49
          },
          "date": "2026-07-24",
          "promotions": []
        }
      ],
      "observed_days": 2,
      "product_key": "gala:store:6:product:275645",
      "retailer_product_id": "275645",
      "sku": "0007615023258",
      "source_id": "275645",
      "source_url": "https://galasupermarkets.com/Freeport-Merrick/category/10578",
      "sp_id": "342825",
      "unit_of_measure": "each",
      "unit_resolution": null,
      "weight": null
    },
    {
      "branch_product_id": null,
      "brand": null,
      "catalog_product_id": "344842",
      "category_paths": [
        "Bakery > Bread & Bagels"
      ],
      "currency": "USD",
      "departments": [
        "Bakery"
      ],
      "description": "Golden Krust Tutti-Fruitti Cake",
      "first_seen": "2026-07-24",
      "has_price_change": false,
      "image_url": "https://galasupermarkets.com/api/content/images/thumbs/0250427_jamaican-bread-golden-krust-tutti-fruitti-cake_300.jpeg",
      "is_active": true,
      "is_current": true,
      "is_visible": true,
      "is_weighable": false,
      "last_seen": "2026-07-24",
      "latest_promotion_count": 0,
      "latest_regular_price": 2.89,
      "name": "Golden Krust Tutti-Fruitti Cake",
      "observations": [
        {
          "catalog": null,
          "date": "2026-07-23",
          "promotions": []
        },
        {
          "catalog": {
            "current_price": 2.89,
            "display_price": "$2.89",
            "is_out_of_stock": null,
            "original_display_price": null,
            "promotion_ids": [],
            "regular_price": 2.89
          },
          "date": "2026-07-24",
          "promotions": []
        }
      ],
      "observed_days": 1,
      "product_key": "gala:store:6:product:277662",
      "retailer_product_id": "277662",
      "sku": "0072113430006",
      "source_id": "277662",
      "source_url": "https://galasupermarkets.com/Freeport-Merrick/category/10466",
      "sp_id": "344842",
      "unit_of_measure": null,
      "unit_resolution": null,
      "weight": null
    },
    {
      "branch_product_id": null,
      "brand": null,
      "catalog_product_id": "345408",
      "category_paths": [
        "Frozen > Ice Cream & Sorbet > Ice Cream Tubs"
      ],
      "currency": "USD",
      "departments": [
        "Frozen"
      ],
      "description": "Lindys Lemon Italian Ice",
      "first_seen": "2026-07-23",
      "has_price_change": false,
      "image_url": "https://galasupermarkets.com/api/content/images/thumbs/0239108_lindys-lindys-lemon-italian-ice_300.jpeg",
      "is_active": true,
      "is_current": true,
      "is_visible": true,
      "is_weighable": false,
      "last_seen": "2026-07-24",
      "latest_promotion_count": 0,
      "latest_regular_price": 4.59,
      "name": "Lindy's Homemade Italian Ice Lemon - 6 Ct, 6 Oz",
      "observations": [
        {
          "catalog": {
            "current_price": 4.59,
            "display_price": "$4.59",
            "is_out_of_stock": null,
            "original_display_price": null,
            "promotion_ids": [],
            "regular_price": 4.59
          },
          "date": "2026-07-23",
          "promotions": []
        },
        {
          "catalog": {
            "current_price": 4.59,
            "display_price": "$4.59",
            "is_out_of_stock": null,
            "original_display_price": null,
            "promotion_ids": [],
            "regular_price": 4.59
          },
          "date": "2026-07-24",
          "promotions": []
        }
      ],
      "observed_days": 2,
      "product_key": "gala:store:6:product:278228",
      "retailer_product_id": "278228",
      "sku": "0081529400007",
      "source_id": "278228",
      "source_url": "https://galasupermarkets.com/Freeport-Merrick/category/10457",
      "sp_id": "345408",
      "unit_of_measure": null,
      "unit_resolution": null,
      "weight": null
    },
    {
      "branch_product_id": null,
      "brand": null,
      "catalog_product_id": "346678",
      "category_paths": [
        "Grocery > Snacks > Chips"
      ],
      "currency": "USD",
      "departments": [
        "Grocery"
      ],
      "description": "Gh Veggie Chips",
      "first_seen": "2026-07-23",
      "has_price_change": false,
      "image_url": "https://galasupermarkets.com/api/content/images/thumbs/0265850_good-health-gh-veggie-chips_300.jpeg",
      "is_active": true,
      "is_current": true,
      "is_visible": true,
      "is_weighable": false,
      "last_seen": "2026-07-24",
      "latest_promotion_count": 0,
      "latest_regular_price": 3.99,
      "name": "Good Health Veggie Chips Sea Salt, 6.75 Oz",
      "observations": [
        {
          "catalog": {
            "current_price": 3.99,
            "display_price": "$3.99",
            "is_out_of_stock": null,
            "original_display_price": null,
            "promotion_ids": [],
            "regular_price": 3.99
          },
          "date": "2026-07-23",
          "promotions": []
        },
        {
          "catalog": {
            "current_price": 3.99,
            "display_price": "$3.99",
            "is_out_of_stock": null,
            "original_display_price": null,
            "promotion_ids": [],
            "regular_price": 3.99
          },
          "date": "2026-07-24",
          "promotions": []
        }
      ],
      "observed_days": 2,
      "product_key": "gala:store:6:product:279498",
      "retailer_product_id": "279498",
      "sku": "0075535500515",
      "source_id": "279498",
      "source_url": "https://galasupermarkets.com/Freeport-Merrick/category/10626",
      "sp_id": "346678",
      "unit_of_measure": null,
      "unit_resolution": null,
      "weight": null
    },
    {
      "branch_product_id": null,
      "brand": null,
      "catalog_product_id": "347942",
      "category_paths": [
        "Grocery > Beans & Grains > Rice"
      ],
      "currency": "USD",
      "departments": [
        "Grocery"
      ],
      "description": "Goya Rice Jasmin",
      "first_seen": "2026-07-23",
      "has_price_change": false,
      "image_url": "https://galasupermarkets.com/api/content/images/thumbs/0245580_jasmine-rice-goya-rice-jasmin_300.jpeg",
      "is_active": true,
      "is_current": true,
      "is_visible": true,
      "is_weighable": false,
      "last_seen": "2026-07-24",
      "latest_promotion_count": 0,
      "latest_regular_price": 4.99,
      "name": "Goya Rice Jasmin",
      "observations": [
        {
          "catalog": {
            "current_price": 4.99,
            "display_price": "$4.99",
            "is_out_of_stock": null,
            "original_display_price": null,
            "promotion_ids": [],
            "regular_price": 4.99
          },
          "date": "2026-07-23",
          "promotions": []
        },
        {
          "catalog": {
            "current_price": 4.99,
            "display_price": "$4.99",
            "is_out_of_stock": null,
            "original_display_price": null,
            "promotion_ids": [],
            "regular_price": 4.99
          },
          "date": "2026-07-24",
          "promotions": []
        }
      ],
      "observed_days": 2,
      "product_key": "gala:store:6:product:280762",
      "retailer_product_id": "280762",
      "sku": "0004133102622",
      "source_id": "280762",
      "source_url": "https://galasupermarkets.com/Freeport-Merrick/category/10511",
      "sp_id": "347942",
      "unit_of_measure": null,
      "unit_resolution": null,
      "weight": null
    },
    {
      "branch_product_id": null,
      "brand": null,
      "catalog_product_id": "348112",
      "category_paths": [
        "Grocery > Dressing & Sauces > Mustard"
      ],
      "currency": "USD",
      "departments": [
        "Grocery"
      ],
      "description": "Bh Mustard Honey Squeezeable",
      "first_seen": "2026-07-23",
      "has_price_change": false,
      "image_url": "https://galasupermarkets.com/api/content/images/thumbs/0245793_boars-head-bh-mustard-honey-squeezeable_300.jpeg",
      "is_active": true,
      "is_current": true,
      "is_visible": true,
      "is_weighable": false,
      "last_seen": "2026-07-24",
      "latest_promotion_count": 0,
      "latest_regular_price": 4.49,
      "name": "Boar's Head Mustard Honey, 10.5 Oz",
      "observations": [
        {
          "catalog": {
            "current_price": 4.49,
            "display_price": "$4.49",
            "is_out_of_stock": null,
            "original_display_price": null,
            "promotion_ids": [],
            "regular_price": 4.49
          },
          "date": "2026-07-23",
          "promotions": []
        },
        {
          "catalog": {
            "current_price": 4.49,
            "display_price": "$4.49",
            "is_out_of_stock": null,
            "original_display_price": null,
            "promotion_ids": [],
            "regular_price": 4.49
          },
          "date": "2026-07-24",
          "promotions": []
        }
      ],
      "observed_days": 2,
      "product_key": "gala:store:6:product:280932",
      "retailer_product_id": "280932",
      "sku": "0004242116002",
      "source_id": "280932",
      "source_url": "https://galasupermarkets.com/Freeport-Merrick/category/10504",
      "sp_id": "348112",
      "unit_of_measure": null,
      "unit_resolution": null,
      "weight": null
    },
    {
      "branch_product_id": null,
      "brand": null,
      "catalog_product_id": "348152",
      "category_paths": [
        "Grocery > Drink Mix"
      ],
      "currency": "USD",
      "departments": [
        "Grocery"
      ],
      "description": "Kool Aid Tropical Punch Can",
      "first_seen": "2026-07-23",
      "has_price_change": false,
      "image_url": "https://galasupermarkets.com/api/content/images/thumbs/0253340_kool-aid-kool-aid-tropical-punch-can_300.jpeg",
      "is_active": true,
      "is_current": true,
      "is_visible": true,
      "is_weighable": false,
      "last_seen": "2026-07-24",
      "latest_promotion_count": 0,
      "latest_regular_price": 5.99,
      "name": "Kool Aid Tropical Punch 8 Qt, 19 Oz",
      "observations": [
        {
          "catalog": {
            "current_price": 5.99,
            "display_price": "$5.99",
            "is_out_of_stock": null,
            "original_display_price": null,
            "promotion_ids": [],
            "regular_price": 5.99
          },
          "date": "2026-07-23",
          "promotions": []
        },
        {
          "catalog": {
            "current_price": 5.99,
            "display_price": "$5.99",
            "is_out_of_stock": null,
            "original_display_price": null,
            "promotion_ids": [],
            "regular_price": 5.99
          },
          "date": "2026-07-24",
          "promotions": []
        }
      ],
      "observed_days": 2,
      "product_key": "gala:store:6:product:280972",
      "retailer_product_id": "280972",
      "sku": "0004300095350",
      "source_id": "280972",
      "source_url": "https://galasupermarkets.com/Freeport-Merrick/category/10495",
      "sp_id": "348152",
      "unit_of_measure": null,
      "unit_resolution": null,
      "weight": null
    },
    {
      "branch_product_id": null,
      "brand": null,
      "catalog_product_id": "350662",
      "category_paths": [
        "Grocery > Coffee, Tea & Cocoa > Tea"
      ],
      "currency": "USD",
      "departments": [
        "Grocery"
      ],
      "description": "Yogi Tea Chamomile",
      "first_seen": "2026-07-23",
      "has_price_change": false,
      "image_url": "https://galasupermarkets.com/api/content/images/thumbs/0260152_yogi-tea-chamomile_300.jpeg",
      "is_active": true,
      "is_current": true,
      "is_visible": true,
      "is_weighable": false,
      "last_seen": "2026-07-24",
      "latest_promotion_count": 0,
      "latest_regular_price": 5.79,
      "name": "Yogi Tea Comfrtng Chamoni Org, 16 Ct",
      "observations": [
        {
          "catalog": {
            "current_price": 5.79,
            "display_price": "$5.79",
            "is_out_of_stock": null,
            "original_display_price": null,
            "promotion_ids": [],
            "regular_price": 5.79
          },
          "date": "2026-07-23",
          "promotions": []
        },
        {
          "catalog": {
            "current_price": 5.79,
            "display_price": "$5.79",
            "is_out_of_stock": null,
            "original_display_price": null,
            "promotion_ids": [],
            "regular_price": 5.79
          },
          "date": "2026-07-24",
          "promotions": []
        }
      ],
      "observed_days": 2,
      "product_key": "gala:store:6:product:283482",
      "retailer_product_id": "283482",
      "sku": "0007695045046",
      "source_id": "283482",
      "source_url": "https://galasupermarkets.com/Freeport-Merrick/category/10523",
      "sp_id": "350662",
      "unit_of_measure": null,
      "unit_resolution": null,
      "weight": null
    },
    {
      "branch_product_id": null,
      "brand": null,
      "catalog_product_id": "351698",
      "category_paths": [
        "Grocery > Beans & Grains > Rice"
      ],
      "currency": "USD",
      "departments": [
        "Grocery"
      ],
      "description": "Goya Brown Rice",
      "first_seen": "2026-07-23",
      "has_price_change": false,
      "image_url": "https://galasupermarkets.com/api/content/images/thumbs/0245560_goya-brown-rice_300.jpeg",
      "is_active": true,
      "is_current": true,
      "is_visible": true,
      "is_weighable": false,
      "last_seen": "2026-07-24",
      "latest_promotion_count": 0,
      "latest_regular_price": 7.29,
      "name": "Goya Brown Rice",
      "observations": [
        {
          "catalog": {
            "current_price": 7.29,
            "display_price": "$7.29",
            "is_out_of_stock": null,
            "original_display_price": null,
            "promotion_ids": [],
            "regular_price": 7.29
          },
          "date": "2026-07-23",
          "promotions": []
        },
        {
          "catalog": {
            "current_price": 7.29,
            "display_price": "$7.29",
            "is_out_of_stock": null,
            "original_display_price": null,
            "promotion_ids": [],
            "regular_price": 7.29
          },
          "date": "2026-07-24",
          "promotions": []
        }
      ],
      "observed_days": 2,
      "product_key": "gala:store:6:product:284518",
      "retailer_product_id": "284518",
      "sku": "0004133102621",
      "source_id": "284518",
      "source_url": "https://galasupermarkets.com/Freeport-Merrick/category/10511",
      "sp_id": "351698",
      "unit_of_measure": null,
      "unit_resolution": null,
      "weight": null
    },
    {
      "branch_product_id": null,
      "brand": null,
      "catalog_product_id": "351726",
      "category_paths": [
        "Grocery > Canned Goods > Canned Tomato"
      ],
      "currency": "USD",
      "departments": [
        "Grocery"
      ],
      "description": "Goya Tomato Sauce",
      "first_seen": "2026-07-23",
      "has_price_change": false,
      "image_url": "https://galasupermarkets.com/api/content/images/thumbs/0245647_goya-tomato-sauce_300.jpeg",
      "is_active": true,
      "is_current": true,
      "is_visible": true,
      "is_weighable": false,
      "last_seen": "2026-07-24",
      "latest_promotion_count": 0,
      "latest_regular_price": 1.99,
      "name": "Goya Tomato Sauce, 15 Oz",
      "observations": [
        {
          "catalog": {
            "current_price": 1.99,
            "display_price": "$1.99",
            "is_out_of_stock": null,
            "original_display_price": null,
            "promotion_ids": [],
            "regular_price": 1.99
          },
          "date": "2026-07-23",
          "promotions": []
        },
        {
          "catalog": {
            "current_price": 1.99,
            "display_price": "$1.99",
            "is_out_of_stock": null,
            "original_display_price": null,
            "promotion_ids": [],
            "regular_price": 1.99
          },
          "date": "2026-07-24",
          "promotions": []
        }
      ],
      "observed_days": 2,
      "product_key": "gala:store:6:product:284546",
      "retailer_product_id": "284546",
      "sku": "0004133103963",
      "source_id": "284546",
      "source_url": "https://galasupermarkets.com/Freeport-Merrick/category/11117",
      "sp_id": "351726",
      "unit_of_measure": null,
      "unit_resolution": null,
      "weight": null
    },
    {
      "branch_product_id": null,
      "brand": null,
      "catalog_product_id": "351845",
      "category_paths": [
        "Grocery > Instant Meals"
      ],
      "currency": "USD",
      "departments": [
        "Grocery"
      ],
      "description": "Maruchan Instant Beef",
      "first_seen": "2026-07-23",
      "has_price_change": false,
      "image_url": "https://galasupermarkets.com/api/content/images/thumbs/0250284_maruchan-instant-beef_300.jpeg",
      "is_active": true,
      "is_current": true,
      "is_visible": true,
      "is_weighable": false,
      "last_seen": "2026-07-24",
      "latest_promotion_count": 0,
      "latest_regular_price": 0.99,
      "name": "Maruchan Instant Beef",
      "observations": [
        {
          "catalog": {
            "current_price": 0.99,
            "display_price": "$0.99 / each",
            "is_out_of_stock": null,
            "original_display_price": null,
            "promotion_ids": [],
            "regular_price": 0.99
          },
          "date": "2026-07-23",
          "promotions": []
        },
        {
          "catalog": {
            "current_price": 0.99,
            "display_price": "$0.99 / each",
            "is_out_of_stock": null,
            "original_display_price": null,
            "promotion_ids": [],
            "regular_price": 0.99
          },
          "date": "2026-07-24",
          "promotions": []
        }
      ],
      "observed_days": 2,
      "product_key": "gala:store:6:product:284665",
      "retailer_product_id": "284665",
      "sku": "0004178900122",
      "source_id": "284665",
      "source_url": "https://galasupermarkets.com/Freeport-Merrick/category/10510",
      "sp_id": "351845",
      "unit_of_measure": "each",
      "unit_resolution": null,
      "weight": null
    },
    {
      "branch_product_id": null,
      "brand": null,
      "catalog_product_id": "351926",
      "category_paths": [
        "Grocery > Baking Needs > Flour"
      ],
      "currency": "USD",
      "departments": [
        "Grocery"
      ],
      "description": "Bbs Rdmll Gf Almnd Meal",
      "first_seen": "2026-07-23",
      "has_price_change": false,
      "image_url": "https://galasupermarkets.com/api/content/images/thumbs/0238623_bobs-red-mill-bbs-rdmll-gf-almnd-meal_300.jpeg",
      "is_active": true,
      "is_current": true,
      "is_visible": true,
      "is_weighable": false,
      "last_seen": "2026-07-24",
      "latest_promotion_count": 0,
      "latest_regular_price": 13.49,
      "name": "Bbs Rdmll Gf Almnd Meal",
      "observations": [
        {
          "catalog": {
            "current_price": 13.49,
            "display_price": "$13.49",
            "is_out_of_stock": null,
            "original_display_price": null,
            "promotion_ids": [],
            "regular_price": 13.49
          },
          "date": "2026-07-23",
          "promotions": []
        },
        {
          "catalog": {
            "current_price": 13.49,
            "display_price": "$13.49",
            "is_out_of_stock": null,
            "original_display_price": null,
            "promotion_ids": [],
            "regular_price": 13.49
          },
          "date": "2026-07-24",
          "promotions": []
        }
      ],
      "observed_days": 2,
      "product_key": "gala:store:6:product:284746",
      "retailer_product_id": "284746",
      "sku": "0003997802380",
      "source_id": "284746",
      "source_url": "https://galasupermarkets.com/Freeport-Merrick/category/10491",
      "sp_id": "351926",
      "unit_of_measure": null,
      "unit_resolution": null,
      "weight": null
    },
    {
      "branch_product_id": null,
      "brand": null,
      "catalog_product_id": "354191",
      "category_paths": [
        "Grocery > Baking Needs > Jam & Filling"
      ],
      "currency": "USD",
      "departments": [
        "Grocery"
      ],
      "description": null,
      "first_seen": "2026-07-23",
      "has_price_change": false,
      "image_url": "https://galasupermarkets.com/api/content/images/thumbs/0246395_polaner-all-fruit-apricot_300.jpeg",
      "is_active": true,
      "is_current": true,
      "is_visible": true,
      "is_weighable": false,
      "last_seen": "2026-07-24",
      "latest_promotion_count": 0,
      "latest_regular_price": 3.69,
      "name": "Polaner All Fruit Spreadable Fruit Apricot, 10 Oz",
      "observations": [
        {
          "catalog": {
            "current_price": 3.69,
            "display_price": "$3.69",
            "is_out_of_stock": null,
            "original_display_price": null,
            "promotion_ids": [],
            "regular_price": 3.69
          },
          "date": "2026-07-23",
          "promotions": []
        },
        {
          "catalog": {
            "current_price": 3.69,
            "display_price": "$3.69",
            "is_out_of_stock": null,
            "original_display_price": null,
            "promotion_ids": [],
            "regular_price": 3.69
          },
          "date": "2026-07-24",
          "promotions": []
        }
      ],
      "observed_days": 2,
      "product_key": "gala:store:6:product:287011",
      "retailer_product_id": "287011",
      "sku": "0007240000722",
      "source_id": "287011",
      "source_url": "https://galasupermarkets.com/Freeport-Merrick/category/10498",
      "sp_id": "354191",
      "unit_of_measure": null,
      "unit_resolution": null,
      "weight": null
    },
    {
      "branch_product_id": null,
      "brand": null,
      "catalog_product_id": "355298",
      "category_paths": [
        "Grocery > Instant Meals"
      ],
      "currency": "USD",
      "departments": [
        "Grocery"
      ],
      "description": "Goya Polvo Encono Cubito",
      "first_seen": "2026-07-23",
      "has_price_change": false,
      "image_url": "https://galasupermarkets.com/api/content/images/thumbs/0245716_goya-polvo-encono-cubito_300.jpeg",
      "is_active": true,
      "is_current": true,
      "is_visible": true,
      "is_weighable": false,
      "last_seen": "2026-07-24",
      "latest_promotion_count": 1,
      "latest_regular_price": 3.59,
      "name": "Goya Chicken Bouillon Powdered, 7.05 Oz",
      "observations": [
        {
          "catalog": {
            "current_price": 7.0,
            "display_price": "$7.00",
            "is_out_of_stock": null,
            "original_display_price": "$3.59",
            "promotion_ids": [
              "multi_buy:eb9f5b8dd0ce623e"
            ],
            "regular_price": 3.59
          },
          "date": "2026-07-23",
          "promotions": [
            {
              "derivation_basis": "explicit source quantity 2 for total $7",
              "derived_effective_unit_price": 3.5,
              "description": "2 for $7",
              "promotion_id": "multi_buy:eb9f5b8dd0ce623e"
            }
          ]
        },
        {
          "catalog": {
            "current_price": 5.0,
            "display_price": "$5.00",
            "is_out_of_stock": null,
            "original_display_price": "$3.59",
            "promotion_ids": [
              "multi_buy:355b3f192d277365"
            ],
            "regular_price": 3.59
          },
          "date": "2026-07-24",
          "promotions": [
            {
              "derivation_basis": "explicit source quantity 2 for total $5",
              "derived_effective_unit_price": 2.5,
              "description": "2 for $5",
              "promotion_id": "multi_buy:355b3f192d277365"
            }
          ]
        }
      ],
      "observed_days": 2,
      "product_key": "gala:store:6:product:288118",
      "retailer_product_id": "288118",
      "sku": "0004133103246",
      "source_id": "288118",
      "source_url": "https://galasupermarkets.com/Freeport-Merrick/category/10510",
      "sp_id": "355298",
      "unit_of_measure": null,
      "unit_resolution": null,
      "weight": null
    },
    {
      "branch_product_id": null,
      "brand": null,
      "catalog_product_id": "356010",
      "category_paths": [
        "Grocery > Snacks > Variety Snacks"
      ],
      "currency": "USD",
      "departments": [
        "Grocery"
      ],
      "description": "Slim Jim Orig Giant Stick",
      "first_seen": "2026-07-23",
      "has_price_change": false,
      "image_url": "https://galasupermarkets.com/api/content/images/thumbs/0267656_slim-jim-original-smoked-snack-stick-097-oz_300.jpeg",
      "is_active": true,
      "is_current": true,
      "is_visible": true,
      "is_weighable": false,
      "last_seen": "2026-07-24",
      "latest_promotion_count": 0,
      "latest_regular_price": 2.19,
      "name": "Slim Jim Original Smoked Snack Stick, 0.97 Oz",
      "observations": [
        {
          "catalog": {
            "current_price": 2.19,
            "display_price": "$2.19",
            "is_out_of_stock": null,
            "original_display_price": null,
            "promotion_ids": [],
            "regular_price": 2.19
          },
          "date": "2026-07-23",
          "promotions": []
        },
        {
          "catalog": {
            "current_price": 2.19,
            "display_price": "$2.19",
            "is_out_of_stock": null,
            "original_display_price": null,
            "promotion_ids": [],
            "regular_price": 2.19
          },
          "date": "2026-07-24",
          "promotions": []
        }
      ],
      "observed_days": 2,
      "product_key": "gala:store:6:product:288830",
      "retailer_product_id": "288830",
      "sku": "0002620011700",
      "source_id": "288830",
      "source_url": "https://galasupermarkets.com/Freeport-Merrick/category/10582",
      "sp_id": "356010",
      "unit_of_measure": null,
      "unit_resolution": null,
      "weight": null
    },
    {
      "branch_product_id": null,
      "brand": null,
      "catalog_product_id": "358530",
      "category_paths": [
        "Grocery > Spices"
      ],
      "currency": "USD",
      "departments": [
        "Grocery"
      ],
      "description": "Old El Paso Taco Season Orig",
      "first_seen": "2026-07-23",
      "has_price_change": false,
      "image_url": "https://galasupermarkets.com/api/content/images/thumbs/0242588_seasonings-old-el-paso-taco-season-orig_300.jpeg",
      "is_active": true,
      "is_current": true,
      "is_visible": true,
      "is_weighable": false,
      "last_seen": "2026-07-24",
      "latest_promotion_count": 0,
      "latest_regular_price": 1.79,
      "name": "Old El Paso Taco Original Seasoning Mix, 1 Oz, 1 Oz",
      "observations": [
        {
          "catalog": {
            "current_price": 1.79,
            "display_price": "$1.79",
            "is_out_of_stock": null,
            "original_display_price": null,
            "promotion_ids": [],
            "regular_price": 1.79
          },
          "date": "2026-07-23",
          "promotions": []
        },
        {
          "catalog": {
            "current_price": 1.79,
            "display_price": "$1.79",
            "is_out_of_stock": null,
            "original_display_price": null,
            "promotion_ids": [],
            "regular_price": 1.79
          },
          "date": "2026-07-24",
          "promotions": []
        }
      ],
      "observed_days": 2,
      "product_key": "gala:store:6:product:291350",
      "retailer_product_id": "291350",
      "sku": "0004600028869",
      "source_id": "291350",
      "source_url": "https://galasupermarkets.com/Freeport-Merrick/category/10517",
      "sp_id": "358530",
      "unit_of_measure": null,
      "unit_resolution": null,
      "weight": null
    },
    {
      "branch_product_id": null,
      "brand": null,
      "catalog_product_id": "358634",
      "category_paths": [
        "Grocery > Baking Needs > Sugar"
      ],
      "currency": "USD",
      "departments": [
        "Grocery"
      ],
      "description": "Premium Pure Cane Sugar",
      "first_seen": "2026-07-23",
      "has_price_change": false,
      "image_url": "https://galasupermarkets.com/api/content/images/thumbs/0259366_domino-sugar-1lb_300.jpeg",
      "is_active": true,
      "is_current": true,
      "is_visible": true,
      "is_weighable": false,
      "last_seen": "2026-07-24",
      "latest_promotion_count": 0,
      "latest_regular_price": 2.29,
      "name": "Domino Premium Pure Cane Sugar, 1 Lb",
      "observations": [
        {
          "catalog": {
            "current_price": 2.29,
            "display_price": "$2.29",
            "is_out_of_stock": null,
            "original_display_price": null,
            "promotion_ids": [],
            "regular_price": 2.29
          },
          "date": "2026-07-23",
          "promotions": []
        },
        {
          "catalog": {
            "current_price": 2.29,
            "display_price": "$2.29",
            "is_out_of_stock": null,
            "original_display_price": null,
            "promotion_ids": [],
            "regular_price": 2.29
          },
          "date": "2026-07-24",
          "promotions": []
        }
      ],
      "observed_days": 2,
      "product_key": "gala:store:6:product:291454",
      "retailer_product_id": "291454",
      "sku": "0004920004201",
      "source_id": "291454",
      "source_url": "https://galasupermarkets.com/Freeport-Merrick/category/10611",
      "sp_id": "358634",
      "unit_of_measure": null,
      "unit_resolution": null,
      "weight": null
    },
    {
      "branch_product_id": null,
      "brand": null,
      "catalog_product_id": "359556",
      "category_paths": [
        "Grocery > Crackers & Flatbread"
      ],
      "currency": "USD",
      "departments": [
        "Grocery"
      ],
      "description": "Cheezit Original Big Crckr",
      "first_seen": "2026-07-23",
      "has_price_change": false,
      "image_url": "https://galasupermarkets.com/api/content/images/thumbs/0277608_cheez-it-baked-snack-crackers-big-117-oz_300.jpeg",
      "is_active": true,
      "is_current": true,
      "is_visible": true,
      "is_weighable": false,
      "last_seen": "2026-07-24",
      "latest_promotion_count": 0,
      "latest_regular_price": 6.49,
      "name": "Cheez-It Baked Snack Crackers Big, 11.7 Oz",
      "observations": [
        {
          "catalog": {
            "current_price": 6.49,
            "display_price": "$6.49",
            "is_out_of_stock": null,
            "original_display_price": null,
            "promotion_ids": [],
            "regular_price": 6.49
          },
          "date": "2026-07-23",
          "promotions": []
        },
        {
          "catalog": {
            "current_price": 6.49,
            "display_price": "$6.49",
            "is_out_of_stock": null,
            "original_display_price": null,
            "promotion_ids": [],
            "regular_price": 6.49
          },
          "date": "2026-07-24",
          "promotions": []
        }
      ],
      "observed_days": 2,
      "product_key": "gala:store:6:product:292376",
      "retailer_product_id": "292376",
      "sku": "0002410059441",
      "source_id": "292376",
      "source_url": "https://galasupermarkets.com/Freeport-Merrick/category/10569",
      "sp_id": "359556",
      "unit_of_measure": null,
      "unit_resolution": null,
      "weight": null
    },
    {
      "branch_product_id": null,
      "brand": null,
      "catalog_product_id": "360304",
      "category_paths": [
        "Grocery > Beverages > Drinks"
      ],
      "currency": "USD",
      "departments": [
        "Grocery"
      ],
      "description": "Bb Drink",
      "first_seen": "2026-07-23",
      "has_price_change": false,
      "image_url": "https://galasupermarkets.com/api/content/images/thumbs/0250718_bb-bb-drink_300.jpeg",
      "is_active": true,
      "is_current": true,
      "is_visible": true,
      "is_weighable": false,
      "last_seen": "2026-07-24",
      "latest_promotion_count": 0,
      "latest_regular_price": 6.79,
      "name": "B&B Orgeat Drink",
      "observations": [
        {
          "catalog": {
            "current_price": 6.79,
            "display_price": "$6.79",
            "is_out_of_stock": null,
            "original_display_price": null,
            "promotion_ids": [],
            "regular_price": 6.79
          },
          "date": "2026-07-23",
          "promotions": []
        },
        {
          "catalog": {
            "current_price": 6.79,
            "display_price": "$6.79",
            "is_out_of_stock": null,
            "original_display_price": null,
            "promotion_ids": [],
            "regular_price": 6.79
          },
          "date": "2026-07-24",
          "promotions": []
        }
      ],
      "observed_days": 2,
      "product_key": "gala:store:6:product:293124",
      "retailer_product_id": "293124",
      "sku": "0073877705018",
      "source_id": "293124",
      "source_url": "https://galasupermarkets.com/Freeport-Merrick/category/10390",
      "sp_id": "360304",
      "unit_of_measure": null,
      "unit_resolution": null,
      "weight": null
    },
    {
      "branch_product_id": null,
      "brand": null,
      "catalog_product_id": "360436",
      "category_paths": [
        "Grocery > Beverages > Soy, Rice & Almond Milk"
      ],
      "currency": "USD",
      "departments": [
        "Grocery"
      ],
      "description": null,
      "first_seen": "2026-07-23",
      "has_price_change": false,
      "image_url": "https://galasupermarkets.com/api/content/images/thumbs/0264104_califia-farms-califia-simply-coconut_300.jpeg",
      "is_active": true,
      "is_current": true,
      "is_visible": true,
      "is_weighable": false,
      "last_seen": "2026-07-24",
      "latest_promotion_count": 0,
      "latest_regular_price": 4.99,
      "name": "Califia Coconut Milk, 48 Oz",
      "observations": [
        {
          "catalog": {
            "current_price": 4.99,
            "display_price": "$4.99",
            "is_out_of_stock": null,
            "original_display_price": null,
            "promotion_ids": [],
            "regular_price": 4.99
          },
          "date": "2026-07-23",
          "promotions": []
        },
        {
          "catalog": {
            "current_price": 4.99,
            "display_price": "$4.99",
            "is_out_of_stock": null,
            "original_display_price": null,
            "promotion_ids": [],
            "regular_price": 4.99
          },
          "date": "2026-07-24",
          "promotions": []
        }
      ],
      "observed_days": 2,
      "product_key": "gala:store:6:product:293256",
      "retailer_product_id": "293256",
      "sku": "0081363602063",
      "source_id": "293256",
      "source_url": "https://galasupermarkets.com/Freeport-Merrick/category/10385",
      "sp_id": "360436",
      "unit_of_measure": null,
      "unit_resolution": null,
      "weight": null
    },
    {
      "branch_product_id": null,
      "brand": null,
      "catalog_product_id": "361892",
      "category_paths": [
        "Grocery > Spices"
      ],
      "currency": "USD",
      "departments": [
        "Grocery"
      ],
      "description": "Old Bay Seasoning",
      "first_seen": "2026-07-23",
      "has_price_change": false,
      "image_url": "https://galasupermarkets.com/api/content/images/thumbs/0239515_old-bay-seasoning_300.jpeg",
      "is_active": true,
      "is_current": true,
      "is_visible": true,
      "is_weighable": false,
      "last_seen": "2026-07-24",
      "latest_promotion_count": 0,
      "latest_regular_price": 7.29,
      "name": "Old Bay Seasoning, 6 Oz",
      "observations": [
        {
          "catalog": {
            "current_price": 7.29,
            "display_price": "$7.29",
            "is_out_of_stock": null,
            "original_display_price": null,
            "promotion_ids": [],
            "regular_price": 7.29
          },
          "date": "2026-07-23",
          "promotions": []
        },
        {
          "catalog": {
            "current_price": 7.29,
            "display_price": "$7.29",
            "is_out_of_stock": null,
            "original_display_price": null,
            "promotion_ids": [],
            "regular_price": 7.29
          },
          "date": "2026-07-24",
          "promotions": []
        }
      ],
      "observed_days": 2,
      "product_key": "gala:store:6:product:294712",
      "retailer_product_id": "294712",
      "sku": "0007032800523",
      "source_id": "294712",
      "source_url": "https://galasupermarkets.com/Freeport-Merrick/category/10517",
      "sp_id": "361892",
      "unit_of_measure": null,
      "unit_resolution": null,
      "weight": null
    },
    {
      "branch_product_id": null,
      "brand": null,
      "catalog_product_id": "363198",
      "category_paths": [
        "Grocery > Canned Goods > Canned Fruits"
      ],
      "currency": "USD",
      "departments": [
        "Grocery"
      ],
      "description": "Del Monte Yel Clng Hlf Peach",
      "first_seen": "2026-07-23",
      "has_price_change": false,
      "image_url": "https://galasupermarkets.com/api/content/images/thumbs/0277411_del-monte-california-yellow-cling-peach-halves-in-heavy-syrup-29-oz_300.jpeg",
      "is_active": true,
      "is_current": true,
      "is_visible": true,
      "is_weighable": false,
      "last_seen": "2026-07-24",
      "latest_promotion_count": 0,
      "latest_regular_price": 4.59,
      "name": "Del Monte California Yellow Cling Peach Halves In Heavy Syrup 29 Oz",
      "observations": [
        {
          "catalog": {
            "current_price": 4.59,
            "display_price": "$4.59",
            "is_out_of_stock": null,
            "original_display_price": null,
            "promotion_ids": [],
            "regular_price": 4.59
          },
          "date": "2026-07-23",
          "promotions": []
        },
        {
          "catalog": {
            "current_price": 4.59,
            "display_price": "$4.59",
            "is_out_of_stock": null,
            "original_display_price": null,
            "promotion_ids": [],
            "regular_price": 4.59
          },
          "date": "2026-07-24",
          "promotions": []
        }
      ],
      "observed_days": 2,
      "product_key": "gala:store:6:product:296018",
      "retailer_product_id": "296018",
      "sku": "0002400001041",
      "source_id": "296018",
      "source_url": "https://galasupermarkets.com/Freeport-Merrick/category/10675",
      "sp_id": "363198",
      "unit_of_measure": null,
      "unit_resolution": null,
      "weight": null
    },
    {
      "branch_product_id": null,
      "brand": null,
      "catalog_product_id": "363679",
      "category_paths": [
        "Grocery > Beverages > Beer"
      ],
      "currency": "USD",
      "departments": [
        "Grocery"
      ],
      "description": "Bud Beer 12Pk 12Oz",
      "first_seen": "2026-07-23",
      "has_price_change": false,
      "image_url": "https://galasupermarkets.com/api/content/images/thumbs/0276313_bud-beer-12-oz_300.jpeg",
      "is_active": true,
      "is_current": true,
      "is_visible": true,
      "is_weighable": false,
      "last_seen": "2026-07-24",
      "latest_promotion_count": 0,
      "latest_regular_price": 15.99,
      "name": "Bud Beer, 12 Oz",
      "observations": [
        {
          "catalog": {
            "current_price": 15.99,
            "display_price": "$15.99",
            "is_out_of_stock": null,
            "original_display_price": null,
            "promotion_ids": [],
            "regular_price": 15.99
          },
          "date": "2026-07-23",
          "promotions": []
        },
        {
          "catalog": {
            "current_price": 15.99,
            "display_price": "$15.99",
            "is_out_of_stock": null,
            "original_display_price": null,
            "promotion_ids": [],
            "regular_price": 15.99
          },
          "date": "2026-07-24",
          "promotions": []
        }
      ],
      "observed_days": 2,
      "product_key": "gala:store:6:product:296499",
      "retailer_product_id": "296499",
      "sku": "0001820011047",
      "source_id": "296499",
      "source_url": "https://galasupermarkets.com/Freeport-Merrick/category/10383",
      "sp_id": "363679",
      "unit_of_measure": null,
      "unit_resolution": null,
      "weight": null
    },
    {
      "branch_product_id": null,
      "brand": null,
      "catalog_product_id": "557980",
      "category_paths": [
        "Grocery > Snacks > Variety Snacks"
      ],
      "currency": "USD",
      "departments": [
        "Grocery"
      ],
      "description": null,
      "first_seen": "2026-07-23",
      "has_price_change": false,
      "image_url": "https://galasupermarkets.com/api/content/images/thumbs/0237426_bagel-bites-bagel-5cheese-18-ct-14-oz_300.jpeg",
      "is_active": true,
      "is_current": true,
      "is_visible": true,
      "is_weighable": false,
      "last_seen": "2026-07-24",
      "latest_promotion_count": 0,
      "latest_regular_price": 7.69,
      "name": "Ore Ida Bagel Bites Three Cheese Pizza Snacks Family Size, 18 Ct",
      "observations": [
        {
          "catalog": {
            "current_price": 7.69,
            "display_price": "$7.69",
            "is_out_of_stock": null,
            "original_display_price": null,
            "promotion_ids": [],
            "regular_price": 7.69
          },
          "date": "2026-07-23",
          "promotions": []
        },
        {
          "catalog": {
            "current_price": 7.69,
            "display_price": "$7.69",
            "is_out_of_stock": null,
            "original_display_price": null,
            "promotion_ids": [],
            "regular_price": 7.69
          },
          "date": "2026-07-24",
          "promotions": []
        }
      ],
      "observed_days": 2,
      "product_key": "gala:store:6:product:299789",
      "retailer_product_id": "299789",
      "sku": "0007008503535",
      "source_id": "299789",
      "source_url": "https://galasupermarkets.com/Freeport-Merrick/category/10582",
      "sp_id": "557980",
      "unit_of_measure": null,
      "unit_resolution": null,
      "weight": null
    },
    {
      "branch_product_id": null,
      "brand": null,
      "catalog_product_id": "508708",
      "category_paths": [
        "Dairy > Pudding"
      ],
      "currency": "USD",
      "departments": [
        "Dairy"
      ],
      "description": "Raymundos Caramel Flan 24 Oz",
      "first_seen": "2026-07-23",
      "has_price_change": false,
      "image_url": "https://galasupermarkets.com/api/content/images/thumbs/682C5148-3962-44D2-88F9-3477E8CCEDD8_GF-image-coming-soon.jpeg",
      "is_active": true,
      "is_current": true,
      "is_visible": true,
      "is_weighable": false,
      "last_seen": "2026-07-24",
      "latest_promotion_count": 0,
      "latest_regular_price": 5.99,
      "name": "Raymundo's Caramel Flan, 24 Oz",
      "observations": [
        {
          "catalog": {
            "current_price": 5.99,
            "display_price": "$5.99",
            "is_out_of_stock": null,
            "original_display_price": null,
            "promotion_ids": [],
            "regular_price": 5.99
          },
          "date": "2026-07-23",
          "promotions": []
        },
        {
          "catalog": {
            "current_price": 5.99,
            "display_price": "$5.99",
            "is_out_of_stock": null,
            "original_display_price": null,
            "promotion_ids": [],
            "regular_price": 5.99
          },
          "date": "2026-07-24",
          "promotions": []
        }
      ],
      "observed_days": 2,
      "product_key": "gala:store:6:product:302935",
      "retailer_product_id": "302935",
      "sku": "0063345605008",
      "source_id": "302935",
      "source_url": "https://galasupermarkets.com/Freeport-Merrick/category/11079",
      "sp_id": "508708",
      "unit_of_measure": null,
      "unit_resolution": null,
      "weight": null
    },
    {
      "branch_product_id": null,
      "brand": null,
      "catalog_product_id": "460427",
      "category_paths": [
        "Grocery > Beverages > Soda"
      ],
      "currency": "USD",
      "departments": [
        "Grocery"
      ],
      "description": "Pol Sp Regular Sprk5l 8Pk",
      "first_seen": "2026-07-23",
      "has_price_change": false,
      "image_url": "https://galasupermarkets.com/api/content/images/thumbs/0237698_poland-spring-pol-sp-regular-sprk5l-8pk_300.jpeg",
      "is_active": true,
      "is_current": true,
      "is_visible": true,
      "is_weighable": false,
      "last_seen": "2026-07-24",
      "latest_promotion_count": 0,
      "latest_regular_price": 4.99,
      "name": "Poland Spring Sparkling Water, Simply Bubbles, 16.9 Oz",
      "observations": [
        {
          "catalog": {
            "current_price": 4.99,
            "display_price": "$4.99",
            "is_out_of_stock": null,
            "original_display_price": null,
            "promotion_ids": [],
            "regular_price": 4.99
          },
          "date": "2026-07-23",
          "promotions": []
        },
        {
          "catalog": {
            "current_price": 4.99,
            "display_price": "$4.99",
            "is_out_of_stock": null,
            "original_display_price": null,
            "promotion_ids": [],
            "regular_price": 4.99
          },
          "date": "2026-07-24",
          "promotions": []
        }
      ],
      "observed_days": 2,
      "product_key": "gala:store:6:product:306180",
      "retailer_product_id": "306180",
      "sku": "0007572044621",
      "source_id": "306180",
      "source_url": "https://galasupermarkets.com/Freeport-Merrick/category/10393",
      "sp_id": "460427",
      "unit_of_measure": null,
      "unit_resolution": null,
      "weight": null
    },
    {
      "branch_product_id": null,
      "brand": null,
      "catalog_product_id": "669836",
      "category_paths": [
        "Frozen > Pancakes & Waffles"
      ],
      "currency": "USD",
      "departments": [
        "Frozen"
      ],
      "description": null,
      "first_seen": "2026-07-23",
      "has_price_change": false,
      "image_url": "https://galasupermarkets.com/api/content/images/thumbs/0239006_de-wafelbakkers-de-wafl-brk-btmlk-pnck-18-pk_300.jpeg",
      "is_active": true,
      "is_current": true,
      "is_visible": true,
      "is_weighable": false,
      "last_seen": "2026-07-24",
      "latest_promotion_count": 0,
      "latest_regular_price": 5.79,
      "name": "De Wafelbakkers Buttermilk Pancakes 18 Ct Bag",
      "observations": [
        {
          "catalog": {
            "current_price": 5.79,
            "display_price": "$5.79",
            "is_out_of_stock": null,
            "original_display_price": null,
            "promotion_ids": [],
            "regular_price": 5.79
          },
          "date": "2026-07-23",
          "promotions": []
        },
        {
          "catalog": {
            "current_price": 5.79,
            "display_price": "$5.79",
            "is_out_of_stock": null,
            "original_display_price": null,
            "promotion_ids": [],
            "regular_price": 5.79
          },
          "date": "2026-07-24",
          "promotions": []
        }
      ],
      "observed_days": 2,
      "product_key": "gala:store:6:product:308280",
      "retailer_product_id": "308280",
      "sku": "0067984410457",
      "source_id": "308280",
      "source_url": "https://galasupermarkets.com/Freeport-Merrick/category/11075",
      "sp_id": "669836",
      "unit_of_measure": null,
      "unit_resolution": null,
      "weight": null
    },
    {
      "branch_product_id": null,
      "brand": null,
      "catalog_product_id": "558436",
      "category_paths": [
        "Grocery > Cereal & Breakfast"
      ],
      "currency": "USD",
      "departments": [
        "Grocery"
      ],
      "description": null,
      "first_seen": "2026-07-23",
      "has_price_change": false,
      "image_url": "https://galasupermarkets.com/api/content/images/thumbs/0254450_honey-bunches-of-oats-post-hbo-honey-rsted-granola_300.jpeg",
      "is_active": true,
      "is_current": true,
      "is_visible": true,
      "is_weighable": false,
      "last_seen": "2026-07-24",
      "latest_promotion_count": 0,
      "latest_regular_price": 5.99,
      "name": "Post Honey Bunches Of Oats Crunchy Honey Roasted Granola, 11 Oz",
      "observations": [
        {
          "catalog": {
            "current_price": 5.99,
            "display_price": "$5.99",
            "is_out_of_stock": null,
            "original_display_price": null,
            "promotion_ids": [],
            "regular_price": 5.99
          },
          "date": "2026-07-23",
          "promotions": []
        },
        {
          "catalog": {
            "current_price": 5.99,
            "display_price": "$5.99",
            "is_out_of_stock": null,
            "original_display_price": null,
            "promotion_ids": [],
            "regular_price": 5.99
          },
          "date": "2026-07-24",
          "promotions": []
        }
      ],
      "observed_days": 2,
      "product_key": "gala:store:6:product:310118",
      "retailer_product_id": "310118",
      "sku": "0088491200341",
      "source_id": "310118",
      "source_url": "https://galasupermarkets.com/Freeport-Merrick/category/10486",
      "sp_id": "558436",
      "unit_of_measure": null,
      "unit_resolution": null,
      "weight": null
    },
    {
      "branch_product_id": null,
      "brand": null,
      "catalog_product_id": "554113",
      "category_paths": [
        "Dairy > Iced Coffee"
      ],
      "currency": "USD",
      "departments": [
        "Dairy"
      ],
      "description": null,
      "first_seen": "2026-07-23",
      "has_price_change": false,
      "image_url": "https://galasupermarkets.com/api/content/images/thumbs/0247038_starbucks-iced-coffee-unswt_300.jpeg",
      "is_active": true,
      "is_current": true,
      "is_visible": true,
      "is_weighable": false,
      "last_seen": "2026-07-24",
      "latest_promotion_count": 0,
      "latest_regular_price": 7.79,
      "name": "Starbucks Iced Coffee Unsweetened, 48 Oz",
      "observations": [
        {
          "catalog": {
            "current_price": 7.79,
            "display_price": "$7.79",
            "is_out_of_stock": null,
            "original_display_price": null,
            "promotion_ids": [],
            "regular_price": 7.79
          },
          "date": "2026-07-23",
          "promotions": []
        },
        {
          "catalog": {
            "current_price": 7.79,
            "display_price": "$7.79",
            "is_out_of_stock": null,
            "original_display_price": null,
            "promotion_ids": [],
            "regular_price": 7.79
          },
          "date": "2026-07-24",
          "promotions": []
        }
      ],
      "observed_days": 2,
      "product_key": "gala:store:6:product:340461",
      "retailer_product_id": "340461",
      "sku": "0004850002238",
      "source_id": "340461",
      "source_url": "https://galasupermarkets.com/Freeport-Merrick/category/10670",
      "sp_id": "554113",
      "unit_of_measure": null,
      "unit_resolution": null,
      "weight": null
    },
    {
      "branch_product_id": null,
      "brand": null,
      "catalog_product_id": "595610",
      "category_paths": [
        "Grocery > Cereal & Breakfast"
      ],
      "currency": "USD",
      "departments": [
        "Grocery"
      ],
      "description": null,
      "first_seen": "2026-07-23",
      "has_price_change": false,
      "image_url": "https://galasupermarkets.com/api/content/images/thumbs/0275739_vry-bry-cheerios-cereal-l_300.jpeg",
      "is_active": true,
      "is_current": true,
      "is_visible": true,
      "is_weighable": false,
      "last_seen": "2026-07-24",
      "latest_promotion_count": 0,
      "latest_regular_price": 8.49,
      "name": "Vry Bry Cheerios Cereal L",
      "observations": [
        {
          "catalog": {
            "current_price": 8.49,
            "display_price": "$8.49",
            "is_out_of_stock": null,
            "original_display_price": null,
            "promotion_ids": [],
            "regular_price": 8.49
          },
          "date": "2026-07-23",
          "promotions": []
        },
        {
          "catalog": {
            "current_price": 8.49,
            "display_price": "$8.49",
            "is_out_of_stock": null,
            "original_display_price": null,
            "promotion_ids": [],
            "regular_price": 8.49
          },
          "date": "2026-07-24",
          "promotions": []
        }
      ],
      "observed_days": 2,
      "product_key": "gala:store:6:product:358309",
      "retailer_product_id": "358309",
      "sku": "0001600016349",
      "source_id": "358309",
      "source_url": "https://galasupermarkets.com/Freeport-Merrick/category/10486",
      "sp_id": "595610",
      "unit_of_measure": null,
      "unit_resolution": null,
      "weight": null
    },
    {
      "branch_product_id": null,
      "brand": null,
      "catalog_product_id": "606457",
      "category_paths": [
        "Dairy > Coffee Creamer"
      ],
      "currency": "USD",
      "departments": [
        "Dairy"
      ],
      "description": null,
      "first_seen": "2026-07-23",
      "has_price_change": false,
      "image_url": "https://galasupermarkets.com/api/content/images/thumbs/0261232_califia-farms-califia-oat-creamer-vanilla_300.jpeg",
      "is_active": true,
      "is_current": true,
      "is_visible": true,
      "is_weighable": false,
      "last_seen": "2026-07-24",
      "latest_promotion_count": 1,
      "latest_regular_price": 6.49,
      "name": "Califia Oat Creamer Vanilla",
      "observations": [
        {
          "catalog": {
            "current_price": 4.99,
            "display_price": "$4.99",
            "is_out_of_stock": null,
            "original_display_price": "$6.49",
            "promotion_ids": [
              "sale:1d19dfa867dcb35b"
            ],
            "regular_price": 6.49
          },
          "date": "2026-07-23",
          "promotions": [
            {
              "derivation_basis": "explicit P_v sale price",
              "derived_effective_unit_price": 4.99,
              "description": "Sale $4.99 (regular $6.49)",
              "promotion_id": "sale:1d19dfa867dcb35b"
            }
          ]
        },
        {
          "catalog": {
            "current_price": 4.99,
            "display_price": "$4.99",
            "is_out_of_stock": null,
            "original_display_price": "$6.49",
            "promotion_ids": [
              "sale:1d19dfa867dcb35b"
            ],
            "regular_price": 6.49
          },
          "date": "2026-07-24",
          "promotions": [
            {
              "derivation_basis": "explicit P_v sale price",
              "derived_effective_unit_price": 4.99,
              "description": "Sale $4.99 (regular $6.49)",
              "promotion_id": "sale:1d19dfa867dcb35b"
            }
          ]
        }
      ],
      "observed_days": 2,
      "product_key": "gala:store:6:product:363623",
      "retailer_product_id": "363623",
      "sku": "0081363602222",
      "source_id": "363623",
      "source_url": "https://galasupermarkets.com/Freeport-Merrick/category/11080",
      "sp_id": "606457",
      "unit_of_measure": null,
      "unit_resolution": null,
      "weight": null
    },
    {
      "branch_product_id": null,
      "brand": null,
      "catalog_product_id": "615308",
      "category_paths": [
        "Health & Beauty > First Aid"
      ],
      "currency": "USD",
      "departments": [
        "Health & Beauty"
      ],
      "description": null,
      "first_seen": "2026-07-23",
      "has_price_change": false,
      "image_url": "https://galasupermarkets.com/api/content/images/thumbs/0238143_health-ade-kombucha-hlth-kombch-gngr-lemon-org_300.jpeg",
      "is_active": true,
      "is_current": true,
      "is_visible": true,
      "is_weighable": false,
      "last_seen": "2026-07-24",
      "latest_promotion_count": 0,
      "latest_regular_price": 3.99,
      "name": "Hlth Kombch Gngr Lemon Org",
      "observations": [
        {
          "catalog": {
            "current_price": 3.99,
            "display_price": "$3.99",
            "is_out_of_stock": null,
            "original_display_price": null,
            "promotion_ids": [],
            "regular_price": 3.99
          },
          "date": "2026-07-23",
          "promotions": []
        },
        {
          "catalog": {
            "current_price": 3.99,
            "display_price": "$3.99",
            "is_out_of_stock": null,
            "original_display_price": null,
            "promotion_ids": [],
            "regular_price": 3.99
          },
          "date": "2026-07-24",
          "promotions": []
        }
      ],
      "observed_days": 2,
      "product_key": "gala:store:6:product:368317",
      "retailer_product_id": "368317",
      "sku": "0085186100609",
      "source_id": "368317",
      "source_url": "https://galasupermarkets.com/Freeport-Merrick/category/10532",
      "sp_id": "615308",
      "unit_of_measure": null,
      "unit_resolution": null,
      "weight": null
    },
    {
      "branch_product_id": null,
      "brand": null,
      "catalog_product_id": "346757",
      "category_paths": [
        "Meat > Chicken"
      ],
      "currency": "USD",
      "departments": [
        "Meat"
      ],
      "description": null,
      "first_seen": "2026-07-23",
      "has_price_change": false,
      "image_url": "https://galasupermarkets.com/api/content/images/thumbs/682C5148-3962-44D2-88F9-3477E8CCEDD8_GF-image-coming-soon.jpeg",
      "is_active": true,
      "is_current": true,
      "is_visible": true,
      "is_weighable": true,
      "last_seen": "2026-07-24",
      "latest_promotion_count": 0,
      "latest_regular_price": 1.99,
      "name": "Fowl Whole fresh",
      "observations": [
        {
          "catalog": {
            "current_price": 1.99,
            "display_price": "$1.99 / lb",
            "is_out_of_stock": null,
            "original_display_price": null,
            "promotion_ids": [],
            "regular_price": 1.99
          },
          "date": "2026-07-23",
          "promotions": []
        },
        {
          "catalog": {
            "current_price": 1.99,
            "display_price": "$1.99 / lb",
            "is_out_of_stock": null,
            "original_display_price": null,
            "promotion_ids": [],
            "regular_price": 1.99
          },
          "date": "2026-07-24",
          "promotions": []
        }
      ],
      "observed_days": 2,
      "product_key": "gala:store:6:product:372852",
      "retailer_product_id": "372852",
      "sku": "0020091700000",
      "source_id": "372852",
      "source_url": "https://galasupermarkets.com/Freeport-Merrick/category/10648",
      "sp_id": "346757",
      "unit_of_measure": "lb",
      "unit_resolution": null,
      "weight": null
    },
    {
      "branch_product_id": null,
      "brand": null,
      "catalog_product_id": "335678",
      "category_paths": [
        "Fruit > Tropical & Specialty"
      ],
      "currency": "USD",
      "departments": [
        "Fruit"
      ],
      "description": null,
      "first_seen": "2026-07-23",
      "has_price_change": false,
      "image_url": "https://galasupermarkets.com/api/content/images/thumbs/0182768_grooved-coconut_300.jpeg",
      "is_active": true,
      "is_current": true,
      "is_visible": true,
      "is_weighable": false,
      "last_seen": "2026-07-24",
      "latest_promotion_count": 0,
      "latest_regular_price": 2.49,
      "name": "Grooved Coconut",
      "observations": [
        {
          "catalog": {
            "current_price": 2.49,
            "display_price": "$2.49 / each",
            "is_out_of_stock": null,
            "original_display_price": null,
            "promotion_ids": [],
            "regular_price": 2.49
          },
          "date": "2026-07-23",
          "promotions": []
        },
        {
          "catalog": {
            "current_price": 2.49,
            "display_price": "$2.49 / each",
            "is_out_of_stock": null,
            "original_display_price": null,
            "promotion_ids": [],
            "regular_price": 2.49
          },
          "date": "2026-07-24",
          "promotions": []
        }
      ],
      "observed_days": 2,
      "product_key": "gala:store:6:product:375269",
      "retailer_product_id": "375269",
      "sku": "0000000004260",
      "source_id": "375269",
      "source_url": "https://galasupermarkets.com/Freeport-Merrick/category/11013",
      "sp_id": "335678",
      "unit_of_measure": "each",
      "unit_resolution": null,
      "weight": null
    }
  ],
  "schema_version": "1.1"
}
