{
  "items": [
    {
      "branch_product_id": null,
      "brand": null,
      "catalog_product_id": "336261",
      "category_paths": [
        "Baby Care > Baby Food"
      ],
      "currency": "USD",
      "departments": [
        "Baby Care"
      ],
      "description": null,
      "first_seen": "2026-07-23",
      "has_price_change": false,
      "image_url": "https://galasupermarkets.com/api/content/images/thumbs/0275452_gerber-2nd-foods-beef-and-gravy-25-oz_300.jpeg",
      "is_active": true,
      "is_current": true,
      "is_visible": true,
      "is_weighable": false,
      "last_seen": "2026-07-23",
      "latest_promotion_count": 0,
      "latest_regular_price": 1.89,
      "name": "Gerber 2nd Foods Beef And Gravy, 2.5 Oz",
      "observations": [
        {
          "catalog": {
            "current_price": 1.89,
            "display_price": "$1.89",
            "is_out_of_stock": null,
            "original_display_price": null,
            "promotion_ids": [],
            "regular_price": 1.89
          },
          "date": "2026-07-23",
          "promotions": []
        }
      ],
      "observed_days": 1,
      "product_key": "gala:store:6:product:269081",
      "retailer_product_id": "269081",
      "sku": "0001500001214",
      "source_id": "269081",
      "source_url": "https://galasupermarkets.com/Freeport-Merrick/category/10375",
      "sp_id": "336261",
      "unit_of_measure": null,
      "unit_resolution": null,
      "weight": null
    },
    {
      "branch_product_id": null,
      "brand": null,
      "catalog_product_id": "336863",
      "category_paths": [
        "Grocery > Instant Meals"
      ],
      "currency": "USD",
      "departments": [
        "Grocery"
      ],
      "description": "Kraft Spiral Mac Cheese",
      "first_seen": "2026-07-23",
      "has_price_change": false,
      "image_url": "https://galasupermarkets.com/api/content/images/thumbs/0276877_kraft-macaroni-cheese-spirals-55-oz_300.jpeg",
      "is_active": true,
      "is_current": true,
      "is_visible": true,
      "is_weighable": false,
      "last_seen": "2026-07-23",
      "latest_promotion_count": 0,
      "latest_regular_price": 2.39,
      "name": "Kraft Macaroni & Cheese Spirals, 5.5 Oz",
      "observations": [
        {
          "catalog": {
            "current_price": 2.39,
            "display_price": "$2.39",
            "is_out_of_stock": null,
            "original_display_price": null,
            "promotion_ids": [],
            "regular_price": 2.39
          },
          "date": "2026-07-23",
          "promotions": []
        }
      ],
      "observed_days": 1,
      "product_key": "gala:store:6:product:269683",
      "retailer_product_id": "269683",
      "sku": "0002100065897",
      "source_id": "269683",
      "source_url": "https://galasupermarkets.com/Freeport-Merrick/category/10510",
      "sp_id": "336863",
      "unit_of_measure": null,
      "unit_resolution": null,
      "weight": null
    },
    {
      "branch_product_id": null,
      "brand": null,
      "catalog_product_id": "338723",
      "category_paths": [
        "Grocery > Canned Goods > Canned Vegetables"
      ],
      "currency": "USD",
      "departments": [
        "Grocery"
      ],
      "description": null,
      "first_seen": "2026-07-23",
      "has_price_change": false,
      "image_url": "https://galasupermarkets.com/api/content/images/thumbs/0264797_libbys-libbys-mixed-veg_300.jpeg",
      "is_active": true,
      "is_current": true,
      "is_visible": true,
      "is_weighable": false,
      "last_seen": "2026-07-23",
      "latest_promotion_count": 1,
      "latest_regular_price": 1.99,
      "name": "Libby's Mixed Vegetables, 15 Oz",
      "observations": [
        {
          "catalog": {
            "current_price": 5.0,
            "display_price": "$5.00",
            "is_out_of_stock": null,
            "original_display_price": "$1.99",
            "promotion_ids": [
              "multi_buy:194a2136cb70ba6e"
            ],
            "regular_price": 1.99
          },
          "date": "2026-07-23",
          "promotions": [
            {
              "derivation_basis": "explicit source quantity 3 for total $5",
              "derived_effective_unit_price": 1.6667,
              "description": "3 for $5",
              "promotion_id": "multi_buy:194a2136cb70ba6e"
            }
          ]
        }
      ],
      "observed_days": 1,
      "product_key": "gala:store:6:product:271543",
      "retailer_product_id": "271543",
      "sku": "0003710003817",
      "source_id": "271543",
      "source_url": "https://galasupermarkets.com/Freeport-Merrick/category/10676",
      "sp_id": "338723",
      "unit_of_measure": null,
      "unit_resolution": null,
      "weight": null
    },
    {
      "branch_product_id": null,
      "brand": null,
      "catalog_product_id": "339213",
      "category_paths": [
        "Dairy > Coffee Creamer"
      ],
      "currency": "USD",
      "departments": [
        "Dairy"
      ],
      "description": "Coffee Creamer French Vanilla",
      "first_seen": "2026-07-23",
      "has_price_change": false,
      "image_url": "https://galasupermarkets.com/api/content/images/thumbs/0245429_international-delight-intl-del-french-vanilla-crmr_300.jpeg",
      "is_active": true,
      "is_current": true,
      "is_visible": true,
      "is_weighable": false,
      "last_seen": "2026-07-23",
      "latest_promotion_count": 0,
      "latest_regular_price": 3.99,
      "name": "International Delight Coffee Creamer French Vanilla, 16 Oz",
      "observations": [
        {
          "catalog": {
            "current_price": 3.99,
            "display_price": "$3.99 / each",
            "is_out_of_stock": null,
            "original_display_price": null,
            "promotion_ids": [],
            "regular_price": 3.99
          },
          "date": "2026-07-23",
          "promotions": []
        }
      ],
      "observed_days": 1,
      "product_key": "gala:store:6:product:272033",
      "retailer_product_id": "272033",
      "sku": "0004127102562",
      "source_id": "272033",
      "source_url": "https://galasupermarkets.com/Freeport-Merrick/category/11080",
      "sp_id": "339213",
      "unit_of_measure": "each",
      "unit_resolution": null,
      "weight": null
    },
    {
      "branch_product_id": null,
      "brand": null,
      "catalog_product_id": "339376",
      "category_paths": [
        "Grocery > Spices"
      ],
      "currency": "USD",
      "departments": [
        "Grocery"
      ],
      "description": "Goya Sazonador Wpep",
      "first_seen": "2026-07-23",
      "has_price_change": false,
      "image_url": "https://galasupermarkets.com/api/content/images/thumbs/0268229_goya-sazonador-wpep_300.jpeg",
      "is_active": true,
      "is_current": true,
      "is_visible": true,
      "is_weighable": false,
      "last_seen": "2026-07-23",
      "latest_promotion_count": 0,
      "latest_regular_price": 5.39,
      "name": "Goya Sazonador Wpep",
      "observations": [
        {
          "catalog": {
            "current_price": 5.39,
            "display_price": "$5.39",
            "is_out_of_stock": null,
            "original_display_price": null,
            "promotion_ids": [],
            "regular_price": 5.39
          },
          "date": "2026-07-23",
          "promotions": []
        }
      ],
      "observed_days": 1,
      "product_key": "gala:store:6:product:272196",
      "retailer_product_id": "272196",
      "sku": "0004133103802",
      "source_id": "272196",
      "source_url": "https://galasupermarkets.com/Freeport-Merrick/category/10517",
      "sp_id": "339376",
      "unit_of_measure": null,
      "unit_resolution": null,
      "weight": null
    },
    {
      "branch_product_id": null,
      "brand": null,
      "catalog_product_id": "339469",
      "category_paths": [
        "Grocery > Canned Goods > Canned Beans & Peas"
      ],
      "currency": "USD",
      "departments": [
        "Grocery"
      ],
      "description": "Goya Frijolsed",
      "first_seen": "2026-07-23",
      "has_price_change": false,
      "image_url": "https://galasupermarkets.com/api/content/images/thumbs/0236154_goya-frijolsed_300.jpeg",
      "is_active": true,
      "is_current": true,
      "is_visible": true,
      "is_weighable": false,
      "last_seen": "2026-07-23",
      "latest_promotion_count": 0,
      "latest_regular_price": 2.29,
      "name": "Goya Central American Red Beans, 15.5 Oz",
      "observations": [
        {
          "catalog": {
            "current_price": 2.29,
            "display_price": "$2.29",
            "is_out_of_stock": null,
            "original_display_price": null,
            "promotion_ids": [],
            "regular_price": 2.29
          },
          "date": "2026-07-23",
          "promotions": []
        }
      ],
      "observed_days": 1,
      "product_key": "gala:store:6:product:272289",
      "retailer_product_id": "272289",
      "sku": "0004133112463",
      "source_id": "272289",
      "source_url": "https://galasupermarkets.com/Freeport-Merrick/category/11206",
      "sp_id": "339469",
      "unit_of_measure": null,
      "unit_resolution": null,
      "weight": null
    },
    {
      "branch_product_id": null,
      "brand": null,
      "catalog_product_id": "340860",
      "category_paths": [
        "Grocery > Baking Needs > Jam & Filling"
      ],
      "currency": "USD",
      "departments": [
        "Grocery"
      ],
      "description": null,
      "first_seen": "2026-07-23",
      "has_price_change": false,
      "image_url": "https://galasupermarkets.com/api/content/images/thumbs/0241686_smuckers-smuckers-sugr-free-grape-jam_300.jpeg",
      "is_active": true,
      "is_current": true,
      "is_visible": true,
      "is_weighable": false,
      "last_seen": "2026-07-23",
      "latest_promotion_count": 0,
      "latest_regular_price": 4.49,
      "name": "Smucker's Jam Concord Grape Sugar Free, 12.75 Oz",
      "observations": [
        {
          "catalog": {
            "current_price": 4.49,
            "display_price": "$4.49",
            "is_out_of_stock": null,
            "original_display_price": null,
            "promotion_ids": [],
            "regular_price": 4.49
          },
          "date": "2026-07-23",
          "promotions": []
        }
      ],
      "observed_days": 1,
      "product_key": "gala:store:6:product:273680",
      "retailer_product_id": "273680",
      "sku": "0005150004005",
      "source_id": "273680",
      "source_url": "https://galasupermarkets.com/Freeport-Merrick/category/10498",
      "sp_id": "340860",
      "unit_of_measure": null,
      "unit_resolution": null,
      "weight": null
    },
    {
      "branch_product_id": null,
      "brand": null,
      "catalog_product_id": "342929",
      "category_paths": [
        "Grocery > Pasta & Noodles"
      ],
      "currency": "USD",
      "departments": [
        "Grocery"
      ],
      "description": "Barilla Pasta Farfalle",
      "first_seen": "2026-07-23",
      "has_price_change": false,
      "image_url": "https://galasupermarkets.com/api/content/images/thumbs/0260330_barilla-pasta-farfalle_300.jpeg",
      "is_active": true,
      "is_current": true,
      "is_visible": true,
      "is_weighable": false,
      "last_seen": "2026-07-23",
      "latest_promotion_count": 0,
      "latest_regular_price": 2.19,
      "name": "Barilla Rigatoni Farfalle, 1 Lb",
      "observations": [
        {
          "catalog": {
            "current_price": 2.19,
            "display_price": "$2.19",
            "is_out_of_stock": null,
            "original_display_price": null,
            "promotion_ids": [],
            "regular_price": 2.19
          },
          "date": "2026-07-23",
          "promotions": []
        }
      ],
      "observed_days": 1,
      "product_key": "gala:store:6:product:275749",
      "retailer_product_id": "275749",
      "sku": "0007680850108",
      "source_id": "275749",
      "source_url": "https://galasupermarkets.com/Freeport-Merrick/category/10505",
      "sp_id": "342929",
      "unit_of_measure": null,
      "unit_resolution": null,
      "weight": null
    },
    {
      "branch_product_id": null,
      "brand": null,
      "catalog_product_id": "343097",
      "category_paths": [
        "Grocery > Beverages > Seltzer"
      ],
      "currency": "USD",
      "departments": [
        "Grocery"
      ],
      "description": "Canada Dry Black Cherry Selt",
      "first_seen": "2026-07-23",
      "has_price_change": false,
      "image_url": "https://galasupermarkets.com/api/content/images/thumbs/0266426_canada-dry-black-cherry-selt_300.jpeg",
      "is_active": true,
      "is_current": true,
      "is_visible": true,
      "is_weighable": false,
      "last_seen": "2026-07-23",
      "latest_promotion_count": 0,
      "latest_regular_price": 3.29,
      "name": "Canada Dry Seltzer, Black Cherry, 2 Ltr",
      "observations": [
        {
          "catalog": {
            "current_price": 3.29,
            "display_price": "$3.29",
            "is_out_of_stock": null,
            "original_display_price": null,
            "promotion_ids": [],
            "regular_price": 3.29
          },
          "date": "2026-07-23",
          "promotions": []
        }
      ],
      "observed_days": 1,
      "product_key": "gala:store:6:product:275917",
      "retailer_product_id": "275917",
      "sku": "0007800002562",
      "source_id": "275917",
      "source_url": "https://galasupermarkets.com/Freeport-Merrick/category/10392",
      "sp_id": "343097",
      "unit_of_measure": null,
      "unit_resolution": null,
      "weight": null
    },
    {
      "branch_product_id": null,
      "brand": null,
      "catalog_product_id": "347948",
      "category_paths": [
        "Grocery > Beverages > Drinks"
      ],
      "currency": "USD",
      "departments": [
        "Grocery"
      ],
      "description": "Goya Coconut Water 100",
      "first_seen": "2026-07-23",
      "has_price_change": false,
      "image_url": "https://galasupermarkets.com/api/content/images/thumbs/0245512_goya-coconut-water-100_300.jpeg",
      "is_active": true,
      "is_current": true,
      "is_visible": true,
      "is_weighable": false,
      "last_seen": "2026-07-23",
      "latest_promotion_count": 0,
      "latest_regular_price": 4.69,
      "name": "Goya 100% Pure Coconut Water, 33.8 Oz",
      "observations": [
        {
          "catalog": {
            "current_price": 4.69,
            "display_price": "$4.69",
            "is_out_of_stock": null,
            "original_display_price": null,
            "promotion_ids": [],
            "regular_price": 4.69
          },
          "date": "2026-07-23",
          "promotions": []
        }
      ],
      "observed_days": 1,
      "product_key": "gala:store:6:product:280768",
      "retailer_product_id": "280768",
      "sku": "0004133102778",
      "source_id": "280768",
      "source_url": "https://galasupermarkets.com/Freeport-Merrick/category/10390",
      "sp_id": "347948",
      "unit_of_measure": null,
      "unit_resolution": null,
      "weight": null
    },
    {
      "branch_product_id": null,
      "brand": null,
      "catalog_product_id": "349655",
      "category_paths": [
        "Grocery > Spices"
      ],
      "currency": "USD",
      "departments": [
        "Grocery"
      ],
      "description": null,
      "first_seen": "2026-07-23",
      "has_price_change": false,
      "image_url": "https://galasupermarkets.com/api/content/images/thumbs/0255174_sibarita-peru-food-pimienta_300.jpeg",
      "is_active": true,
      "is_current": true,
      "is_visible": true,
      "is_weighable": false,
      "last_seen": "2026-07-23",
      "latest_promotion_count": 0,
      "latest_regular_price": 2.99,
      "name": "Sibarita Pimienta Black Pepper",
      "observations": [
        {
          "catalog": {
            "current_price": 2.99,
            "display_price": "$2.99",
            "is_out_of_stock": null,
            "original_display_price": null,
            "promotion_ids": [],
            "regular_price": 2.99
          },
          "date": "2026-07-23",
          "promotions": []
        }
      ],
      "observed_days": 1,
      "product_key": "gala:store:6:product:282475",
      "retailer_product_id": "282475",
      "sku": "0081212500631",
      "source_id": "282475",
      "source_url": "https://galasupermarkets.com/Freeport-Merrick/category/10517",
      "sp_id": "349655",
      "unit_of_measure": null,
      "unit_resolution": null,
      "weight": null
    },
    {
      "branch_product_id": null,
      "brand": null,
      "catalog_product_id": "349852",
      "category_paths": [
        "Frozen > Ice Cream & Sorbet > Sorbet"
      ],
      "currency": "USD",
      "departments": [
        "Frozen"
      ],
      "description": "Mamita Raspberry Ice",
      "first_seen": "2026-07-23",
      "has_price_change": false,
      "image_url": "https://galasupermarkets.com/api/content/images/thumbs/0256427_mamitas-mamita-raspberry-ice_300.jpeg",
      "is_active": true,
      "is_current": true,
      "is_visible": true,
      "is_weighable": false,
      "last_seen": "2026-07-23",
      "latest_promotion_count": 0,
      "latest_regular_price": 4.99,
      "name": "Mamita's Rasberry Ice, 4 Ct",
      "observations": [
        {
          "catalog": {
            "current_price": 4.99,
            "display_price": "$4.99",
            "is_out_of_stock": null,
            "original_display_price": null,
            "promotion_ids": [],
            "regular_price": 4.99
          },
          "date": "2026-07-23",
          "promotions": []
        }
      ],
      "observed_days": 1,
      "product_key": "gala:store:6:product:282672",
      "retailer_product_id": "282672",
      "sku": "0089279800036",
      "source_id": "282672",
      "source_url": "https://galasupermarkets.com/Freeport-Merrick/category/10459",
      "sp_id": "349852",
      "unit_of_measure": null,
      "unit_resolution": null,
      "weight": null
    },
    {
      "branch_product_id": null,
      "brand": null,
      "catalog_product_id": "352186",
      "category_paths": [
        "Grocery > Baking Needs > Flour"
      ],
      "currency": "USD",
      "departments": [
        "Grocery"
      ],
      "description": "Tamale Mix",
      "first_seen": "2026-07-23",
      "has_price_change": false,
      "image_url": "https://galasupermarkets.com/api/content/images/thumbs/0256479_maseca-tamale-mix_300.jpeg",
      "is_active": true,
      "is_current": true,
      "is_visible": true,
      "is_weighable": false,
      "last_seen": "2026-07-23",
      "latest_promotion_count": 0,
      "latest_regular_price": 6.29,
      "name": "Maseca Tamal Mix, 4.84 Lb",
      "observations": [
        {
          "catalog": {
            "current_price": 6.29,
            "display_price": "$6.29",
            "is_out_of_stock": null,
            "original_display_price": null,
            "promotion_ids": [],
            "regular_price": 6.29
          },
          "date": "2026-07-23",
          "promotions": []
        }
      ],
      "observed_days": 1,
      "product_key": "gala:store:6:product:285006",
      "retailer_product_id": "285006",
      "sku": "0003729794447",
      "source_id": "285006",
      "source_url": "https://galasupermarkets.com/Freeport-Merrick/category/10491",
      "sp_id": "352186",
      "unit_of_measure": null,
      "unit_resolution": null,
      "weight": null
    },
    {
      "branch_product_id": null,
      "brand": null,
      "catalog_product_id": "352627",
      "category_paths": [
        "Grocery > Snacks > Cookies"
      ],
      "currency": "USD",
      "departments": [
        "Grocery"
      ],
      "description": "Bisquick Cmpl Panckewaf Mix",
      "first_seen": "2026-07-23",
      "has_price_change": false,
      "image_url": "https://galasupermarkets.com/api/content/images/thumbs/0275852_betty-crocker-bisquick-baking-mix-complete-pancake-and-waffle-mix-buttermilk-with-whole-grain-28-oz_300.jpeg",
      "is_active": true,
      "is_current": true,
      "is_visible": true,
      "is_weighable": false,
      "last_seen": "2026-07-23",
      "latest_promotion_count": 0,
      "latest_regular_price": 4.59,
      "name": "Betty Crocker Bisquick Baking Mix, Complete Pancake And Waffle Mix, Buttermilk With Whole Grain, 28 Oz",
      "observations": [
        {
          "catalog": {
            "current_price": 4.59,
            "display_price": "$4.59",
            "is_out_of_stock": null,
            "original_display_price": null,
            "promotion_ids": [],
            "regular_price": 4.59
          },
          "date": "2026-07-23",
          "promotions": []
        }
      ],
      "observed_days": 1,
      "product_key": "gala:store:6:product:285447",
      "retailer_product_id": "285447",
      "sku": "0001600042731",
      "source_id": "285447",
      "source_url": "https://galasupermarkets.com/Freeport-Merrick/category/10469",
      "sp_id": "352627",
      "unit_of_measure": null,
      "unit_resolution": null,
      "weight": null
    },
    {
      "branch_product_id": null,
      "brand": null,
      "catalog_product_id": "353890",
      "category_paths": [
        "Fruit > Apples"
      ],
      "currency": "USD",
      "departments": [
        "Fruit"
      ],
      "description": null,
      "first_seen": "2026-07-23",
      "has_price_change": false,
      "image_url": "https://galasupermarkets.com/api/content/images/thumbs/0238831_lil-snappers-lil-snapper-granny-apples_300.jpeg",
      "is_active": true,
      "is_current": true,
      "is_visible": true,
      "is_weighable": false,
      "last_seen": "2026-07-23",
      "latest_promotion_count": 0,
      "latest_regular_price": 6.99,
      "name": "Lil Snappers Apples Granny Smith, 3 Lb",
      "observations": [
        {
          "catalog": {
            "current_price": 6.99,
            "display_price": "$6.99 / each",
            "is_out_of_stock": null,
            "original_display_price": null,
            "promotion_ids": [],
            "regular_price": 6.99
          },
          "date": "2026-07-23",
          "promotions": []
        }
      ],
      "observed_days": 1,
      "product_key": "gala:store:6:product:286710",
      "retailer_product_id": "286710",
      "sku": "0074183900591",
      "source_id": "286710",
      "source_url": "https://galasupermarkets.com/Freeport-Merrick/category/11004",
      "sp_id": "353890",
      "unit_of_measure": "each",
      "unit_resolution": null,
      "weight": null
    },
    {
      "branch_product_id": null,
      "brand": null,
      "catalog_product_id": "354232",
      "category_paths": [
        "Grocery > Canned Goods > Canned Tomato"
      ],
      "currency": "USD",
      "departments": [
        "Grocery"
      ],
      "description": "Red Pack Crushed Tomatoes",
      "first_seen": "2026-07-23",
      "has_price_change": false,
      "image_url": "https://galasupermarkets.com/api/content/images/thumbs/0237612_red-pack-crushed-tomatoes_300.jpeg",
      "is_active": true,
      "is_current": true,
      "is_visible": true,
      "is_weighable": false,
      "last_seen": "2026-07-23",
      "latest_promotion_count": 1,
      "latest_regular_price": 3.69,
      "name": "Red Pack Tomatoes Crushed, 28 Oz",
      "observations": [
        {
          "catalog": {
            "current_price": 7.0,
            "display_price": "$7.00",
            "is_out_of_stock": null,
            "original_display_price": "$3.69",
            "promotion_ids": [
              "multi_buy:b96678d0b42a4068"
            ],
            "regular_price": 3.69
          },
          "date": "2026-07-23",
          "promotions": [
            {
              "derivation_basis": "explicit source quantity 2 for total $7",
              "derived_effective_unit_price": 3.5,
              "description": "2 for $7",
              "promotion_id": "multi_buy:b96678d0b42a4068"
            }
          ]
        }
      ],
      "observed_days": 1,
      "product_key": "gala:store:6:product:287052",
      "retailer_product_id": "287052",
      "sku": "0007294074401",
      "source_id": "287052",
      "source_url": "https://galasupermarkets.com/Freeport-Merrick/category/11117",
      "sp_id": "354232",
      "unit_of_measure": null,
      "unit_resolution": null,
      "weight": null
    },
    {
      "branch_product_id": null,
      "brand": null,
      "catalog_product_id": "358209",
      "category_paths": [
        "Grocery > Canned Goods > Canned Fruits"
      ],
      "currency": "USD",
      "departments": [
        "Grocery"
      ],
      "description": null,
      "first_seen": "2026-07-23",
      "has_price_change": false,
      "image_url": "https://galasupermarkets.com/api/content/images/thumbs/0246412_geisha-mand-oranges_300.jpeg",
      "is_active": true,
      "is_current": true,
      "is_visible": true,
      "is_weighable": false,
      "last_seen": "2026-07-23",
      "latest_promotion_count": 0,
      "latest_regular_price": 1.99,
      "name": "Geisha Mandarin Oranges",
      "observations": [
        {
          "catalog": {
            "current_price": 1.99,
            "display_price": "$1.99",
            "is_out_of_stock": null,
            "original_display_price": null,
            "promotion_ids": [],
            "regular_price": 1.99
          },
          "date": "2026-07-23",
          "promotions": []
        }
      ],
      "observed_days": 1,
      "product_key": "gala:store:6:product:291029",
      "retailer_product_id": "291029",
      "sku": "0007114040110",
      "source_id": "291029",
      "source_url": "https://galasupermarkets.com/Freeport-Merrick/category/10675",
      "sp_id": "358209",
      "unit_of_measure": null,
      "unit_resolution": null,
      "weight": null
    },
    {
      "branch_product_id": null,
      "brand": null,
      "catalog_product_id": "363981",
      "category_paths": [
        "Bakery > Bread & Bagels"
      ],
      "currency": "USD",
      "departments": [
        "Bakery"
      ],
      "description": null,
      "first_seen": "2026-07-23",
      "has_price_change": false,
      "image_url": "https://galasupermarkets.com/api/content/images/thumbs/0244653_natures-own-natures-own-crafted-white_300.jpeg",
      "is_active": true,
      "is_current": true,
      "is_visible": true,
      "is_weighable": false,
      "last_seen": "2026-07-23",
      "latest_promotion_count": 0,
      "latest_regular_price": 4.79,
      "name": "Nature's Own White Bread Thick Sliced, 22 Oz",
      "observations": [
        {
          "catalog": {
            "current_price": 4.79,
            "display_price": "$4.79",
            "is_out_of_stock": null,
            "original_display_price": null,
            "promotion_ids": [],
            "regular_price": 4.79
          },
          "date": "2026-07-23",
          "promotions": []
        }
      ],
      "observed_days": 1,
      "product_key": "gala:store:6:product:296801",
      "retailer_product_id": "296801",
      "sku": "0007225002074",
      "source_id": "296801",
      "source_url": "https://galasupermarkets.com/Freeport-Merrick/category/10466",
      "sp_id": "363981",
      "unit_of_measure": null,
      "unit_resolution": null,
      "weight": null
    },
    {
      "branch_product_id": null,
      "brand": null,
      "catalog_product_id": "559970",
      "category_paths": [
        "Grocery > Beverages > Soda"
      ],
      "currency": "USD",
      "departments": [
        "Grocery"
      ],
      "description": null,
      "first_seen": "2026-07-23",
      "has_price_change": false,
      "image_url": "https://galasupermarkets.com/api/content/images/thumbs/0274519_pepsi-cola-125-liter-bottle_300.jpeg",
      "is_active": true,
      "is_current": true,
      "is_visible": true,
      "is_weighable": false,
      "last_seen": "2026-07-23",
      "latest_promotion_count": 0,
      "latest_regular_price": 2.29,
      "name": "Pepsi Cola 1.25 Liter Bottle",
      "observations": [
        {
          "catalog": {
            "current_price": 2.29,
            "display_price": "$2.29",
            "is_out_of_stock": null,
            "original_display_price": null,
            "promotion_ids": [],
            "regular_price": 2.29
          },
          "date": "2026-07-23",
          "promotions": []
        }
      ],
      "observed_days": 1,
      "product_key": "gala:store:6:product:297299",
      "retailer_product_id": "297299",
      "sku": "0001200014092",
      "source_id": "297299",
      "source_url": "https://galasupermarkets.com/Freeport-Merrick/category/10393",
      "sp_id": "559970",
      "unit_of_measure": null,
      "unit_resolution": null,
      "weight": null
    },
    {
      "branch_product_id": null,
      "brand": null,
      "catalog_product_id": "476476",
      "category_paths": [
        "Grocery > Pasta & Noodles"
      ],
      "currency": "USD",
      "departments": [
        "Grocery"
      ],
      "description": "Barilla Gluten Free Spaghetti 12 Oz",
      "first_seen": "2026-07-23",
      "has_price_change": false,
      "image_url": "https://galasupermarkets.com/api/content/images/thumbs/0263859_pasta-noodles-barilla-gluten-free-spaghetti-12-oz_300.jpeg",
      "is_active": true,
      "is_current": true,
      "is_visible": true,
      "is_weighable": false,
      "last_seen": "2026-07-23",
      "latest_promotion_count": 0,
      "latest_regular_price": 3.79,
      "name": "Barilla Gluten-Free Spaghetti 12 Oz Box",
      "observations": [
        {
          "catalog": {
            "current_price": 3.79,
            "display_price": "$3.79",
            "is_out_of_stock": null,
            "original_display_price": null,
            "promotion_ids": [],
            "regular_price": 3.79
          },
          "date": "2026-07-23",
          "promotions": []
        }
      ],
      "observed_days": 1,
      "product_key": "gala:store:6:product:299023",
      "retailer_product_id": "299023",
      "sku": "0007680800388",
      "source_id": "299023",
      "source_url": "https://galasupermarkets.com/Freeport-Merrick/category/10505",
      "sp_id": "476476",
      "unit_of_measure": null,
      "unit_resolution": null,
      "weight": null
    },
    {
      "branch_product_id": null,
      "brand": null,
      "catalog_product_id": "559991",
      "category_paths": [
        "Grocery > Snacks > Chips"
      ],
      "currency": "USD",
      "departments": [
        "Grocery"
      ],
      "description": null,
      "first_seen": "2026-07-23",
      "has_price_change": false,
      "image_url": "https://galasupermarkets.com/api/content/images/thumbs/0258002_ruffles-baked-chd-sour-cream_300.jpeg",
      "is_active": true,
      "is_current": true,
      "is_visible": true,
      "is_weighable": false,
      "last_seen": "2026-07-23",
      "latest_promotion_count": 0,
      "latest_regular_price": 4.99,
      "name": "Ruffles Oven Baked Cheddar & Sour Cream Potato Crisps, 6.25 Oz",
      "observations": [
        {
          "catalog": {
            "current_price": 4.99,
            "display_price": "$4.99",
            "is_out_of_stock": null,
            "original_display_price": null,
            "promotion_ids": [],
            "regular_price": 4.99
          },
          "date": "2026-07-23",
          "promotions": []
        }
      ],
      "observed_days": 1,
      "product_key": "gala:store:6:product:299313",
      "retailer_product_id": "299313",
      "sku": "0002840018477",
      "source_id": "299313",
      "source_url": "https://galasupermarkets.com/Freeport-Merrick/category/10626",
      "sp_id": "559991",
      "unit_of_measure": null,
      "unit_resolution": null,
      "weight": null
    },
    {
      "branch_product_id": null,
      "brand": null,
      "catalog_product_id": "544052",
      "category_paths": [
        "Household > Cleaning"
      ],
      "currency": "USD",
      "departments": [
        "Household"
      ],
      "description": "Ajax Dish Liquid L",
      "first_seen": "2026-07-23",
      "has_price_change": false,
      "image_url": "https://galasupermarkets.com/api/content/images/thumbs/0258563_ajax-dish-liquid-l_300.jpeg",
      "is_active": true,
      "is_current": true,
      "is_visible": true,
      "is_weighable": false,
      "last_seen": "2026-07-23",
      "latest_promotion_count": 0,
      "latest_regular_price": 9.99,
      "name": "Ajax Dish Liquid L",
      "observations": [
        {
          "catalog": {
            "current_price": 9.99,
            "display_price": "$9.99",
            "is_out_of_stock": null,
            "original_display_price": null,
            "promotion_ids": [],
            "regular_price": 9.99
          },
          "date": "2026-07-23",
          "promotions": []
        }
      ],
      "observed_days": 1,
      "product_key": "gala:store:6:product:301782",
      "retailer_product_id": "301782",
      "sku": "0003500049110",
      "source_id": "301782",
      "source_url": "https://galasupermarkets.com/Freeport-Merrick/category/10408",
      "sp_id": "544052",
      "unit_of_measure": null,
      "unit_resolution": null,
      "weight": null
    },
    {
      "branch_product_id": null,
      "brand": null,
      "catalog_product_id": "558648",
      "category_paths": [
        "Grocery > Pasta & Noodles"
      ],
      "currency": "USD",
      "departments": [
        "Grocery"
      ],
      "description": "Ronzoni Trio Italiano",
      "first_seen": "2026-07-23",
      "has_price_change": false,
      "image_url": "https://galasupermarkets.com/api/content/images/thumbs/0260215_ronzoni-trio-italiano_300.jpeg",
      "is_active": true,
      "is_current": true,
      "is_visible": true,
      "is_weighable": false,
      "last_seen": "2026-07-23",
      "latest_promotion_count": 0,
      "latest_regular_price": 2.19,
      "name": "Ronzoni Trio Italiano, 16 Oz",
      "observations": [
        {
          "catalog": {
            "current_price": 2.19,
            "display_price": "$2.19",
            "is_out_of_stock": null,
            "original_display_price": null,
            "promotion_ids": [],
            "regular_price": 2.19
          },
          "date": "2026-07-23",
          "promotions": []
        }
      ],
      "observed_days": 1,
      "product_key": "gala:store:6:product:311764",
      "retailer_product_id": "311764",
      "sku": "0007130000122",
      "source_id": "311764",
      "source_url": "https://galasupermarkets.com/Freeport-Merrick/category/10505",
      "sp_id": "558648",
      "unit_of_measure": null,
      "unit_resolution": null,
      "weight": null
    },
    {
      "branch_product_id": null,
      "brand": null,
      "catalog_product_id": "630576",
      "category_paths": [
        "Grocery > Canned Goods > Canned Vegetables"
      ],
      "currency": "USD",
      "departments": [
        "Grocery"
      ],
      "description": null,
      "first_seen": "2026-07-23",
      "has_price_change": false,
      "image_url": "https://galasupermarkets.com/api/content/images/thumbs/0277489_del-monte-fresh-cut-chopped-spinach-135-oz_300.jpeg",
      "is_active": true,
      "is_current": true,
      "is_visible": true,
      "is_weighable": false,
      "last_seen": "2026-07-23",
      "latest_promotion_count": 0,
      "latest_regular_price": 2.49,
      "name": "Del Monte Fresh Cut Chopped Spinach, 13.5 Oz",
      "observations": [
        {
          "catalog": {
            "current_price": 2.49,
            "display_price": "$2.49",
            "is_out_of_stock": null,
            "original_display_price": null,
            "promotion_ids": [],
            "regular_price": 2.49
          },
          "date": "2026-07-23",
          "promotions": []
        }
      ],
      "observed_days": 1,
      "product_key": "gala:store:6:product:316616",
      "retailer_product_id": "316616",
      "sku": "0002400016316",
      "source_id": "316616",
      "source_url": "https://galasupermarkets.com/Freeport-Merrick/category/10676",
      "sp_id": "630576",
      "unit_of_measure": null,
      "unit_resolution": null,
      "weight": null
    },
    {
      "branch_product_id": null,
      "brand": null,
      "catalog_product_id": "557146",
      "category_paths": [
        "Grocery > Dressing & Sauces > Soy & Teriyaki Sauce"
      ],
      "currency": "USD",
      "departments": [
        "Grocery"
      ],
      "description": "Soy Vay Very Veri Tryki Ls 21 Oz",
      "first_seen": "2026-07-23",
      "has_price_change": false,
      "image_url": "https://galasupermarkets.com/api/content/images/thumbs/0264943_soy-vay-very-veri-tryki-ls-21-oz_300.jpeg",
      "is_active": true,
      "is_current": true,
      "is_visible": true,
      "is_weighable": false,
      "last_seen": "2026-07-23",
      "latest_promotion_count": 0,
      "latest_regular_price": 6.49,
      "name": "Soyvay Veri Veri Teriaki Less Sodium, 21 Oz",
      "observations": [
        {
          "catalog": {
            "current_price": 6.49,
            "display_price": "$6.49",
            "is_out_of_stock": null,
            "original_display_price": null,
            "promotion_ids": [],
            "regular_price": 6.49
          },
          "date": "2026-07-23",
          "promotions": []
        }
      ],
      "observed_days": 1,
      "product_key": "gala:store:6:product:317560",
      "retailer_product_id": "317560",
      "sku": "0008817722775",
      "source_id": "317560",
      "source_url": "https://galasupermarkets.com/Freeport-Merrick/category/11119",
      "sp_id": "557146",
      "unit_of_measure": null,
      "unit_resolution": null,
      "weight": null
    },
    {
      "branch_product_id": null,
      "brand": null,
      "catalog_product_id": "552601",
      "category_paths": [
        "Grocery > Candy & Sweets > Chocolate"
      ],
      "currency": "USD",
      "departments": [
        "Grocery"
      ],
      "description": "Hersheys Mr Goodbar",
      "first_seen": "2026-07-23",
      "has_price_change": false,
      "image_url": "https://galasupermarkets.com/api/content/images/thumbs/0175812_hersheys-mr-goodbar_300.jpeg",
      "is_active": true,
      "is_current": true,
      "is_visible": true,
      "is_weighable": false,
      "last_seen": "2026-07-23",
      "latest_promotion_count": 0,
      "latest_regular_price": 1.69,
      "name": "Hershey's Mr. Goodbar, 1.75 Oz",
      "observations": [
        {
          "catalog": {
            "current_price": 1.69,
            "display_price": "$1.69",
            "is_out_of_stock": null,
            "original_display_price": null,
            "promotion_ids": [],
            "regular_price": 1.69
          },
          "date": "2026-07-23",
          "promotions": []
        }
      ],
      "observed_days": 1,
      "product_key": "gala:store:6:product:318858",
      "retailer_product_id": "318858",
      "sku": "0003400000243",
      "source_id": "318858",
      "source_url": "https://galasupermarkets.com/Freeport-Merrick/category/10433",
      "sp_id": "552601",
      "unit_of_measure": null,
      "unit_resolution": null,
      "weight": null
    },
    {
      "branch_product_id": null,
      "brand": null,
      "catalog_product_id": "557344",
      "category_paths": [
        "Grocery > Dressing & Sauces > Dressing"
      ],
      "currency": "USD",
      "departments": [
        "Grocery"
      ],
      "description": "Urban Meadow Caesar 16Oz",
      "first_seen": "2026-07-23",
      "has_price_change": false,
      "image_url": "https://galasupermarkets.com/api/content/images/thumbs/682C5148-3962-44D2-88F9-3477E8CCEDD8_GF-image-coming-soon.jpeg",
      "is_active": true,
      "is_current": true,
      "is_visible": true,
      "is_weighable": false,
      "last_seen": "2026-07-23",
      "latest_promotion_count": 0,
      "latest_regular_price": 4.49,
      "name": "Urban Meadow Caesar 16Oz",
      "observations": [
        {
          "catalog": {
            "current_price": 4.49,
            "display_price": "$4.49",
            "is_out_of_stock": null,
            "original_display_price": null,
            "promotion_ids": [],
            "regular_price": 4.49
          },
          "date": "2026-07-23",
          "promotions": []
        }
      ],
      "observed_days": 1,
      "product_key": "gala:store:6:product:332678",
      "retailer_product_id": "332678",
      "sku": "0007329605407",
      "source_id": "332678",
      "source_url": "https://galasupermarkets.com/Freeport-Merrick/category/10494",
      "sp_id": "557344",
      "unit_of_measure": null,
      "unit_resolution": null,
      "weight": null
    },
    {
      "branch_product_id": null,
      "brand": null,
      "catalog_product_id": "602377",
      "category_paths": [
        "Grocery > Baking Needs > Sugar"
      ],
      "currency": "USD",
      "departments": [
        "Grocery"
      ],
      "description": null,
      "first_seen": "2026-07-23",
      "has_price_change": false,
      "image_url": "https://galasupermarkets.com/api/content/images/thumbs/0259736_domino-golden-sugar-175lb-175-lb_300.jpeg",
      "is_active": true,
      "is_current": true,
      "is_visible": true,
      "is_weighable": false,
      "last_seen": "2026-07-23",
      "latest_promotion_count": 0,
      "latest_regular_price": 3.29,
      "name": "Domino Golden Sugar 175Lb 1.75 Lb",
      "observations": [
        {
          "catalog": {
            "current_price": 3.29,
            "display_price": "$3.29",
            "is_out_of_stock": null,
            "original_display_price": null,
            "promotion_ids": [],
            "regular_price": 3.29
          },
          "date": "2026-07-23",
          "promotions": []
        }
      ],
      "observed_days": 1,
      "product_key": "gala:store:6:product:348165",
      "retailer_product_id": "348165",
      "sku": "0004920090498",
      "source_id": "348165",
      "source_url": "https://galasupermarkets.com/Freeport-Merrick/category/10611",
      "sp_id": "602377",
      "unit_of_measure": null,
      "unit_resolution": null,
      "weight": null
    },
    {
      "branch_product_id": null,
      "brand": null,
      "catalog_product_id": "592404",
      "category_paths": [
        "Fruit > Tropical & Specialty"
      ],
      "currency": "USD",
      "departments": [
        "Fruit"
      ],
      "description": null,
      "first_seen": "2026-07-23",
      "has_price_change": false,
      "image_url": "https://galasupermarkets.com/api/content/images/thumbs/0192004_rambutan_300.jpeg",
      "is_active": true,
      "is_current": true,
      "is_visible": true,
      "is_weighable": false,
      "last_seen": "2026-07-23",
      "latest_promotion_count": 0,
      "latest_regular_price": 6.99,
      "name": "Rambutan",
      "observations": [
        {
          "catalog": {
            "current_price": 6.99,
            "display_price": "$6.99",
            "is_out_of_stock": null,
            "original_display_price": null,
            "promotion_ids": [],
            "regular_price": 6.99
          },
          "date": "2026-07-23",
          "promotions": []
        }
      ],
      "observed_days": 1,
      "product_key": "gala:store:6:product:356010",
      "retailer_product_id": "356010",
      "sku": "0000000005091",
      "source_id": "356010",
      "source_url": "https://galasupermarkets.com/Freeport-Merrick/category/11013",
      "sp_id": "592404",
      "unit_of_measure": null,
      "unit_resolution": null,
      "weight": null
    },
    {
      "branch_product_id": null,
      "brand": null,
      "catalog_product_id": "607800",
      "category_paths": [
        "Grocery > Beverages > Juices"
      ],
      "currency": "USD",
      "departments": [
        "Grocery"
      ],
      "description": null,
      "first_seen": "2026-07-23",
      "has_price_change": false,
      "image_url": "https://galasupermarkets.com/api/content/images/thumbs/0249667_honest-kids-org-strwpch-8pk_300.jpeg",
      "is_active": true,
      "is_current": true,
      "is_visible": true,
      "is_weighable": false,
      "last_seen": "2026-07-23",
      "latest_promotion_count": 0,
      "latest_regular_price": 5.49,
      "name": "Honest Kids Org Strwpch 8Pk",
      "observations": [
        {
          "catalog": {
            "current_price": 5.49,
            "display_price": "$5.49",
            "is_out_of_stock": null,
            "original_display_price": null,
            "promotion_ids": [],
            "regular_price": 5.49
          },
          "date": "2026-07-23",
          "promotions": []
        }
      ],
      "observed_days": 1,
      "product_key": "gala:store:6:product:364324",
      "retailer_product_id": "364324",
      "sku": "0065762273094",
      "source_id": "364324",
      "source_url": "https://galasupermarkets.com/Freeport-Merrick/category/10618",
      "sp_id": "607800",
      "unit_of_measure": null,
      "unit_resolution": null,
      "weight": null
    }
  ],
  "schema_version": "1.1"
}
